// 
// Decompiled by Procyon v0.5.36
// 

package kotlin.collections;

import java.util.TreeSet;
import java.util.SortedSet;
import kotlin.TypeCastException;
import java.util.Iterator;
import kotlin.PublishedApi;
import kotlin.internal.InlineOnly;
import kotlin.jvm.JvmName;
import kotlin.SinceKotlin;
import kotlin.internal.PlatformImplementationsKt;
import java.util.Arrays;
import java.util.Comparator;
import java.util.Collection;
import java.util.ArrayList;
import kotlin.jvm.internal.Intrinsics;
import java.util.List;
import org.jetbrains.annotations.NotNull;
import kotlin.Metadata;

@Metadata(mv = { 1, 1, 13 }, bv = { 1, 0, 3 }, k = 5, xi = 1, d1 = { "\u0000\u0096\u0001\n\u0000\n\u0002\u0010 \n\u0000\n\u0002\u0010\u0011\n\u0000\n\u0002\u0010\u000b\n\u0002\u0010\u0018\n\u0002\u0010\u0005\n\u0002\u0010\u0012\n\u0002\u0010\f\n\u0002\u0010\u0019\n\u0002\u0010\u0006\n\u0002\u0010\u0013\n\u0002\u0010\u0007\n\u0002\u0010\u0014\n\u0002\u0010\b\n\u0002\u0010\u0015\n\u0002\u0010\t\n\u0002\u0010\u0016\n\u0002\u0010\n\n\u0002\u0010\u0017\n\u0002\b\u0003\n\u0002\u0018\u0002\n\u0002\u0018\u0002\n\u0002\b\f\n\u0002\u0010\u000e\n\u0002\b\u0014\n\u0002\u0010\u0002\n\u0002\b\u0004\n\u0002\u0018\u0002\n\u0002\b\u0003\n\u0002\u0010\u001f\n\u0002\b\u0005\n\u0002\u0010\u001e\n\u0002\b\u0004\n\u0002\u0010\u000f\n\u0002\b\u0006\n\u0002\u0018\u0002\n\u0002\b\f\u001a#\u0010\u0000\u001a\b\u0012\u0004\u0012\u0002H\u00020\u0001\"\u0004\b\u0000\u0010\u0002*\n\u0012\u0006\b\u0001\u0012\u0002H\u00020\u0003¢\u0006\u0002\u0010\u0004\u001a\u0010\u0010\u0000\u001a\b\u0012\u0004\u0012\u00020\u00050\u0001*\u00020\u0006\u001a\u0010\u0010\u0000\u001a\b\u0012\u0004\u0012\u00020\u00070\u0001*\u00020\b\u001a\u0010\u0010\u0000\u001a\b\u0012\u0004\u0012\u00020\t0\u0001*\u00020\n\u001a\u0010\u0010\u0000\u001a\b\u0012\u0004\u0012\u00020\u000b0\u0001*\u00020\f\u001a\u0010\u0010\u0000\u001a\b\u0012\u0004\u0012\u00020\r0\u0001*\u00020\u000e\u001a\u0010\u0010\u0000\u001a\b\u0012\u0004\u0012\u00020\u000f0\u0001*\u00020\u0010\u001a\u0010\u0010\u0000\u001a\b\u0012\u0004\u0012\u00020\u00110\u0001*\u00020\u0012\u001a\u0010\u0010\u0000\u001a\b\u0012\u0004\u0012\u00020\u00130\u0001*\u00020\u0014\u001aU\u0010\u0015\u001a\u00020\u000f\"\u0004\b\u0000\u0010\u0002*\n\u0012\u0006\b\u0001\u0012\u0002H\u00020\u00032\u0006\u0010\u0016\u001a\u0002H\u00022\u001a\u0010\u0017\u001a\u0016\u0012\u0006\b\u0000\u0012\u0002H\u00020\u0018j\n\u0012\u0006\b\u0000\u0012\u0002H\u0002`\u00192\b\b\u0002\u0010\u001a\u001a\u00020\u000f2\b\b\u0002\u0010\u001b\u001a\u00020\u000f¢\u0006\u0002\u0010\u001c\u001a9\u0010\u0015\u001a\u00020\u000f\"\u0004\b\u0000\u0010\u0002*\n\u0012\u0006\b\u0001\u0012\u0002H\u00020\u00032\u0006\u0010\u0016\u001a\u0002H\u00022\b\b\u0002\u0010\u001a\u001a\u00020\u000f2\b\b\u0002\u0010\u001b\u001a\u00020\u000f¢\u0006\u0002\u0010\u001d\u001a&\u0010\u0015\u001a\u00020\u000f*\u00020\b2\u0006\u0010\u0016\u001a\u00020\u00072\b\b\u0002\u0010\u001a\u001a\u00020\u000f2\b\b\u0002\u0010\u001b\u001a\u00020\u000f\u001a&\u0010\u0015\u001a\u00020\u000f*\u00020\n2\u0006\u0010\u0016\u001a\u00020\t2\b\b\u0002\u0010\u001a\u001a\u00020\u000f2\b\b\u0002\u0010\u001b\u001a\u00020\u000f\u001a&\u0010\u0015\u001a\u00020\u000f*\u00020\f2\u0006\u0010\u0016\u001a\u00020\u000b2\b\b\u0002\u0010\u001a\u001a\u00020\u000f2\b\b\u0002\u0010\u001b\u001a\u00020\u000f\u001a&\u0010\u0015\u001a\u00020\u000f*\u00020\u000e2\u0006\u0010\u0016\u001a\u00020\r2\b\b\u0002\u0010\u001a\u001a\u00020\u000f2\b\b\u0002\u0010\u001b\u001a\u00020\u000f\u001a&\u0010\u0015\u001a\u00020\u000f*\u00020\u00102\u0006\u0010\u0016\u001a\u00020\u000f2\b\b\u0002\u0010\u001a\u001a\u00020\u000f2\b\b\u0002\u0010\u001b\u001a\u00020\u000f\u001a&\u0010\u0015\u001a\u00020\u000f*\u00020\u00122\u0006\u0010\u0016\u001a\u00020\u00112\b\b\u0002\u0010\u001a\u001a\u00020\u000f2\b\b\u0002\u0010\u001b\u001a\u00020\u000f\u001a&\u0010\u0015\u001a\u00020\u000f*\u00020\u00142\u0006\u0010\u0016\u001a\u00020\u00132\b\b\u0002\u0010\u001a\u001a\u00020\u000f2\b\b\u0002\u0010\u001b\u001a\u00020\u000f\u001a2\u0010\u001e\u001a\u00020\u0005\"\u0004\b\u0000\u0010\u0002*\n\u0012\u0006\b\u0001\u0012\u0002H\u00020\u00032\u000e\u0010\u001f\u001a\n\u0012\u0006\b\u0001\u0012\u0002H\u00020\u0003H\u0087\f¢\u0006\u0004\b \u0010!\u001a\"\u0010\"\u001a\u00020\u000f\"\u0004\b\u0000\u0010\u0002*\n\u0012\u0006\b\u0001\u0012\u0002H\u00020\u0003H\u0087\b¢\u0006\u0004\b#\u0010$\u001a\"\u0010%\u001a\u00020&\"\u0004\b\u0000\u0010\u0002*\n\u0012\u0006\b\u0001\u0012\u0002H\u00020\u0003H\u0087\b¢\u0006\u0004\b'\u0010(\u001a0\u0010)\u001a\u00020\u0005\"\u0004\b\u0000\u0010\u0002*\n\u0012\u0006\b\u0001\u0012\u0002H\u00020\u00032\u000e\u0010\u001f\u001a\n\u0012\u0006\b\u0001\u0012\u0002H\u00020\u0003H\u0087\f¢\u0006\u0002\u0010!\u001a\u0015\u0010)\u001a\u00020\u0005*\u00020\u00062\u0006\u0010\u001f\u001a\u00020\u0006H\u0087\f\u001a\u0015\u0010)\u001a\u00020\u0005*\u00020\b2\u0006\u0010\u001f\u001a\u00020\bH\u0087\f\u001a\u0015\u0010)\u001a\u00020\u0005*\u00020\n2\u0006\u0010\u001f\u001a\u00020\nH\u0087\f\u001a\u0015\u0010)\u001a\u00020\u0005*\u00020\f2\u0006\u0010\u001f\u001a\u00020\fH\u0087\f\u001a\u0015\u0010)\u001a\u00020\u0005*\u00020\u000e2\u0006\u0010\u001f\u001a\u00020\u000eH\u0087\f\u001a\u0015\u0010)\u001a\u00020\u0005*\u00020\u00102\u0006\u0010\u001f\u001a\u00020\u0010H\u0087\f\u001a\u0015\u0010)\u001a\u00020\u0005*\u00020\u00122\u0006\u0010\u001f\u001a\u00020\u0012H\u0087\f\u001a\u0015\u0010)\u001a\u00020\u0005*\u00020\u00142\u0006\u0010\u001f\u001a\u00020\u0014H\u0087\f\u001a \u0010*\u001a\u00020\u000f\"\u0004\b\u0000\u0010\u0002*\n\u0012\u0006\b\u0001\u0012\u0002H\u00020\u0003H\u0087\b¢\u0006\u0002\u0010$\u001a\r\u0010*\u001a\u00020\u000f*\u00020\u0006H\u0087\b\u001a\r\u0010*\u001a\u00020\u000f*\u00020\bH\u0087\b\u001a\r\u0010*\u001a\u00020\u000f*\u00020\nH\u0087\b\u001a\r\u0010*\u001a\u00020\u000f*\u00020\fH\u0087\b\u001a\r\u0010*\u001a\u00020\u000f*\u00020\u000eH\u0087\b\u001a\r\u0010*\u001a\u00020\u000f*\u00020\u0010H\u0087\b\u001a\r\u0010*\u001a\u00020\u000f*\u00020\u0012H\u0087\b\u001a\r\u0010*\u001a\u00020\u000f*\u00020\u0014H\u0087\b\u001a \u0010+\u001a\u00020&\"\u0004\b\u0000\u0010\u0002*\n\u0012\u0006\b\u0001\u0012\u0002H\u00020\u0003H\u0087\b¢\u0006\u0002\u0010(\u001a\r\u0010+\u001a\u00020&*\u00020\u0006H\u0087\b\u001a\r\u0010+\u001a\u00020&*\u00020\bH\u0087\b\u001a\r\u0010+\u001a\u00020&*\u00020\nH\u0087\b\u001a\r\u0010+\u001a\u00020&*\u00020\fH\u0087\b\u001a\r\u0010+\u001a\u00020&*\u00020\u000eH\u0087\b\u001a\r\u0010+\u001a\u00020&*\u00020\u0010H\u0087\b\u001a\r\u0010+\u001a\u00020&*\u00020\u0012H\u0087\b\u001a\r\u0010+\u001a\u00020&*\u00020\u0014H\u0087\b\u001aQ\u0010,\u001a\b\u0012\u0004\u0012\u0002H\u00020\u0003\"\u0004\b\u0000\u0010\u0002*\n\u0012\u0006\b\u0001\u0012\u0002H\u00020\u00032\f\u0010-\u001a\b\u0012\u0004\u0012\u0002H\u00020\u00032\b\b\u0002\u0010.\u001a\u00020\u000f2\b\b\u0002\u0010/\u001a\u00020\u000f2\b\b\u0002\u00100\u001a\u00020\u000fH\u0007¢\u0006\u0002\u00101\u001a2\u0010,\u001a\u00020\u0006*\u00020\u00062\u0006\u0010-\u001a\u00020\u00062\b\b\u0002\u0010.\u001a\u00020\u000f2\b\b\u0002\u0010/\u001a\u00020\u000f2\b\b\u0002\u00100\u001a\u00020\u000fH\u0007\u001a2\u0010,\u001a\u00020\b*\u00020\b2\u0006\u0010-\u001a\u00020\b2\b\b\u0002\u0010.\u001a\u00020\u000f2\b\b\u0002\u0010/\u001a\u00020\u000f2\b\b\u0002\u00100\u001a\u00020\u000fH\u0007\u001a2\u0010,\u001a\u00020\n*\u00020\n2\u0006\u0010-\u001a\u00020\n2\b\b\u0002\u0010.\u001a\u00020\u000f2\b\b\u0002\u0010/\u001a\u00020\u000f2\b\b\u0002\u00100\u001a\u00020\u000fH\u0007\u001a2\u0010,\u001a\u00020\f*\u00020\f2\u0006\u0010-\u001a\u00020\f2\b\b\u0002\u0010.\u001a\u00020\u000f2\b\b\u0002\u0010/\u001a\u00020\u000f2\b\b\u0002\u00100\u001a\u00020\u000fH\u0007\u001a2\u0010,\u001a\u00020\u000e*\u00020\u000e2\u0006\u0010-\u001a\u00020\u000e2\b\b\u0002\u0010.\u001a\u00020\u000f2\b\b\u0002\u0010/\u001a\u00020\u000f2\b\b\u0002\u00100\u001a\u00020\u000fH\u0007\u001a2\u0010,\u001a\u00020\u0010*\u00020\u00102\u0006\u0010-\u001a\u00020\u00102\b\b\u0002\u0010.\u001a\u00020\u000f2\b\b\u0002\u0010/\u001a\u00020\u000f2\b\b\u0002\u00100\u001a\u00020\u000fH\u0007\u001a2\u0010,\u001a\u00020\u0012*\u00020\u00122\u0006\u0010-\u001a\u00020\u00122\b\b\u0002\u0010.\u001a\u00020\u000f2\b\b\u0002\u0010/\u001a\u00020\u000f2\b\b\u0002\u00100\u001a\u00020\u000fH\u0007\u001a2\u0010,\u001a\u00020\u0014*\u00020\u00142\u0006\u0010-\u001a\u00020\u00142\b\b\u0002\u0010.\u001a\u00020\u000f2\b\b\u0002\u0010/\u001a\u00020\u000f2\b\b\u0002\u00100\u001a\u00020\u000fH\u0007\u001a$\u00102\u001a\b\u0012\u0004\u0012\u0002H\u00020\u0003\"\u0004\b\u0000\u0010\u0002*\b\u0012\u0004\u0012\u0002H\u00020\u0003H\u0087\b¢\u0006\u0002\u00103\u001a.\u00102\u001a\n\u0012\u0006\u0012\u0004\u0018\u0001H\u00020\u0003\"\u0004\b\u0000\u0010\u0002*\b\u0012\u0004\u0012\u0002H\u00020\u00032\u0006\u00104\u001a\u00020\u000fH\u0087\b¢\u0006\u0002\u00105\u001a\r\u00102\u001a\u00020\u0006*\u00020\u0006H\u0087\b\u001a\u0015\u00102\u001a\u00020\u0006*\u00020\u00062\u0006\u00104\u001a\u00020\u000fH\u0087\b\u001a\r\u00102\u001a\u00020\b*\u00020\bH\u0087\b\u001a\u0015\u00102\u001a\u00020\b*\u00020\b2\u0006\u00104\u001a\u00020\u000fH\u0087\b\u001a\r\u00102\u001a\u00020\n*\u00020\nH\u0087\b\u001a\u0015\u00102\u001a\u00020\n*\u00020\n2\u0006\u00104\u001a\u00020\u000fH\u0087\b\u001a\r\u00102\u001a\u00020\f*\u00020\fH\u0087\b\u001a\u0015\u00102\u001a\u00020\f*\u00020\f2\u0006\u00104\u001a\u00020\u000fH\u0087\b\u001a\r\u00102\u001a\u00020\u000e*\u00020\u000eH\u0087\b\u001a\u0015\u00102\u001a\u00020\u000e*\u00020\u000e2\u0006\u00104\u001a\u00020\u000fH\u0087\b\u001a\r\u00102\u001a\u00020\u0010*\u00020\u0010H\u0087\b\u001a\u0015\u00102\u001a\u00020\u0010*\u00020\u00102\u0006\u00104\u001a\u00020\u000fH\u0087\b\u001a\r\u00102\u001a\u00020\u0012*\u00020\u0012H\u0087\b\u001a\u0015\u00102\u001a\u00020\u0012*\u00020\u00122\u0006\u00104\u001a\u00020\u000fH\u0087\b\u001a\r\u00102\u001a\u00020\u0014*\u00020\u0014H\u0087\b\u001a\u0015\u00102\u001a\u00020\u0014*\u00020\u00142\u0006\u00104\u001a\u00020\u000fH\u0087\b\u001a6\u00106\u001a\b\u0012\u0004\u0012\u0002H\u00020\u0003\"\u0004\b\u0000\u0010\u0002*\b\u0012\u0004\u0012\u0002H\u00020\u00032\u0006\u0010\u001a\u001a\u00020\u000f2\u0006\u0010\u001b\u001a\u00020\u000fH\u0087\b¢\u0006\u0004\b7\u00108\u001a\"\u00106\u001a\u00020\u0006*\u00020\u00062\u0006\u0010\u001a\u001a\u00020\u000f2\u0006\u0010\u001b\u001a\u00020\u000fH\u0087\b¢\u0006\u0002\b7\u001a\"\u00106\u001a\u00020\b*\u00020\b2\u0006\u0010\u001a\u001a\u00020\u000f2\u0006\u0010\u001b\u001a\u00020\u000fH\u0087\b¢\u0006\u0002\b7\u001a\"\u00106\u001a\u00020\n*\u00020\n2\u0006\u0010\u001a\u001a\u00020\u000f2\u0006\u0010\u001b\u001a\u00020\u000fH\u0087\b¢\u0006\u0002\b7\u001a\"\u00106\u001a\u00020\f*\u00020\f2\u0006\u0010\u001a\u001a\u00020\u000f2\u0006\u0010\u001b\u001a\u00020\u000fH\u0087\b¢\u0006\u0002\b7\u001a\"\u00106\u001a\u00020\u000e*\u00020\u000e2\u0006\u0010\u001a\u001a\u00020\u000f2\u0006\u0010\u001b\u001a\u00020\u000fH\u0087\b¢\u0006\u0002\b7\u001a\"\u00106\u001a\u00020\u0010*\u00020\u00102\u0006\u0010\u001a\u001a\u00020\u000f2\u0006\u0010\u001b\u001a\u00020\u000fH\u0087\b¢\u0006\u0002\b7\u001a\"\u00106\u001a\u00020\u0012*\u00020\u00122\u0006\u0010\u001a\u001a\u00020\u000f2\u0006\u0010\u001b\u001a\u00020\u000fH\u0087\b¢\u0006\u0002\b7\u001a\"\u00106\u001a\u00020\u0014*\u00020\u00142\u0006\u0010\u001a\u001a\u00020\u000f2\u0006\u0010\u001b\u001a\u00020\u000fH\u0087\b¢\u0006\u0002\b7\u001a5\u00109\u001a\b\u0012\u0004\u0012\u0002H\u00020\u0003\"\u0004\b\u0000\u0010\u0002*\b\u0012\u0004\u0012\u0002H\u00020\u00032\u0006\u0010\u001a\u001a\u00020\u000f2\u0006\u0010\u001b\u001a\u00020\u000fH\u0001¢\u0006\u0004\b6\u00108\u001a!\u00109\u001a\u00020\u0006*\u00020\u00062\u0006\u0010\u001a\u001a\u00020\u000f2\u0006\u0010\u001b\u001a\u00020\u000fH\u0001¢\u0006\u0002\b6\u001a!\u00109\u001a\u00020\b*\u00020\b2\u0006\u0010\u001a\u001a\u00020\u000f2\u0006\u0010\u001b\u001a\u00020\u000fH\u0001¢\u0006\u0002\b6\u001a!\u00109\u001a\u00020\n*\u00020\n2\u0006\u0010\u001a\u001a\u00020\u000f2\u0006\u0010\u001b\u001a\u00020\u000fH\u0001¢\u0006\u0002\b6\u001a!\u00109\u001a\u00020\f*\u00020\f2\u0006\u0010\u001a\u001a\u00020\u000f2\u0006\u0010\u001b\u001a\u00020\u000fH\u0001¢\u0006\u0002\b6\u001a!\u00109\u001a\u00020\u000e*\u00020\u000e2\u0006\u0010\u001a\u001a\u00020\u000f2\u0006\u0010\u001b\u001a\u00020\u000fH\u0001¢\u0006\u0002\b6\u001a!\u00109\u001a\u00020\u0010*\u00020\u00102\u0006\u0010\u001a\u001a\u00020\u000f2\u0006\u0010\u001b\u001a\u00020\u000fH\u0001¢\u0006\u0002\b6\u001a!\u00109\u001a\u00020\u0012*\u00020\u00122\u0006\u0010\u001a\u001a\u00020\u000f2\u0006\u0010\u001b\u001a\u00020\u000fH\u0001¢\u0006\u0002\b6\u001a!\u00109\u001a\u00020\u0014*\u00020\u00142\u0006\u0010\u001a\u001a\u00020\u000f2\u0006\u0010\u001b\u001a\u00020\u000fH\u0001¢\u0006\u0002\b6\u001a7\u0010:\u001a\u00020;\"\u0004\b\u0000\u0010\u0002*\b\u0012\u0004\u0012\u0002H\u00020\u00032\u0006\u0010\u0016\u001a\u0002H\u00022\b\b\u0002\u0010\u001a\u001a\u00020\u000f2\b\b\u0002\u0010\u001b\u001a\u00020\u000f¢\u0006\u0002\u0010<\u001a&\u0010:\u001a\u00020;*\u00020\u00062\u0006\u0010\u0016\u001a\u00020\u00052\b\b\u0002\u0010\u001a\u001a\u00020\u000f2\b\b\u0002\u0010\u001b\u001a\u00020\u000f\u001a&\u0010:\u001a\u00020;*\u00020\b2\u0006\u0010\u0016\u001a\u00020\u00072\b\b\u0002\u0010\u001a\u001a\u00020\u000f2\b\b\u0002\u0010\u001b\u001a\u00020\u000f\u001a&\u0010:\u001a\u00020;*\u00020\n2\u0006\u0010\u0016\u001a\u00020\t2\b\b\u0002\u0010\u001a\u001a\u00020\u000f2\b\b\u0002\u0010\u001b\u001a\u00020\u000f\u001a&\u0010:\u001a\u00020;*\u00020\f2\u0006\u0010\u0016\u001a\u00020\u000b2\b\b\u0002\u0010\u001a\u001a\u00020\u000f2\b\b\u0002\u0010\u001b\u001a\u00020\u000f\u001a&\u0010:\u001a\u00020;*\u00020\u000e2\u0006\u0010\u0016\u001a\u00020\r2\b\b\u0002\u0010\u001a\u001a\u00020\u000f2\b\b\u0002\u0010\u001b\u001a\u00020\u000f\u001a&\u0010:\u001a\u00020;*\u00020\u00102\u0006\u0010\u0016\u001a\u00020\u000f2\b\b\u0002\u0010\u001a\u001a\u00020\u000f2\b\b\u0002\u0010\u001b\u001a\u00020\u000f\u001a&\u0010:\u001a\u00020;*\u00020\u00122\u0006\u0010\u0016\u001a\u00020\u00112\b\b\u0002\u0010\u001a\u001a\u00020\u000f2\b\b\u0002\u0010\u001b\u001a\u00020\u000f\u001a&\u0010:\u001a\u00020;*\u00020\u00142\u0006\u0010\u0016\u001a\u00020\u00132\b\b\u0002\u0010\u001a\u001a\u00020\u000f2\b\b\u0002\u0010\u001b\u001a\u00020\u000f\u001a-\u0010=\u001a\b\u0012\u0004\u0012\u0002H>0\u0001\"\u0004\b\u0000\u0010>*\u0006\u0012\u0002\b\u00030\u00032\f\u0010?\u001a\b\u0012\u0004\u0012\u0002H>0@¢\u0006\u0002\u0010A\u001aA\u0010B\u001a\u0002HC\"\u0010\b\u0000\u0010C*\n\u0012\u0006\b\u0000\u0012\u0002H>0D\"\u0004\b\u0001\u0010>*\u0006\u0012\u0002\b\u00030\u00032\u0006\u0010-\u001a\u0002HC2\f\u0010?\u001a\b\u0012\u0004\u0012\u0002H>0@¢\u0006\u0002\u0010E\u001a,\u0010F\u001a\b\u0012\u0004\u0012\u0002H\u00020\u0003\"\u0004\b\u0000\u0010\u0002*\b\u0012\u0004\u0012\u0002H\u00020\u00032\u0006\u0010\u0016\u001a\u0002H\u0002H\u0086\u0002¢\u0006\u0002\u0010G\u001a4\u0010F\u001a\b\u0012\u0004\u0012\u0002H\u00020\u0003\"\u0004\b\u0000\u0010\u0002*\b\u0012\u0004\u0012\u0002H\u00020\u00032\u000e\u0010H\u001a\n\u0012\u0006\b\u0001\u0012\u0002H\u00020\u0003H\u0086\u0002¢\u0006\u0002\u0010I\u001a2\u0010F\u001a\b\u0012\u0004\u0012\u0002H\u00020\u0003\"\u0004\b\u0000\u0010\u0002*\b\u0012\u0004\u0012\u0002H\u00020\u00032\f\u0010H\u001a\b\u0012\u0004\u0012\u0002H\u00020JH\u0086\u0002¢\u0006\u0002\u0010K\u001a\u0015\u0010F\u001a\u00020\u0006*\u00020\u00062\u0006\u0010\u0016\u001a\u00020\u0005H\u0086\u0002\u001a\u0015\u0010F\u001a\u00020\u0006*\u00020\u00062\u0006\u0010H\u001a\u00020\u0006H\u0086\u0002\u001a\u001b\u0010F\u001a\u00020\u0006*\u00020\u00062\f\u0010H\u001a\b\u0012\u0004\u0012\u00020\u00050JH\u0086\u0002\u001a\u0015\u0010F\u001a\u00020\b*\u00020\b2\u0006\u0010\u0016\u001a\u00020\u0007H\u0086\u0002\u001a\u0015\u0010F\u001a\u00020\b*\u00020\b2\u0006\u0010H\u001a\u00020\bH\u0086\u0002\u001a\u001b\u0010F\u001a\u00020\b*\u00020\b2\f\u0010H\u001a\b\u0012\u0004\u0012\u00020\u00070JH\u0086\u0002\u001a\u0015\u0010F\u001a\u00020\n*\u00020\n2\u0006\u0010\u0016\u001a\u00020\tH\u0086\u0002\u001a\u0015\u0010F\u001a\u00020\n*\u00020\n2\u0006\u0010H\u001a\u00020\nH\u0086\u0002\u001a\u001b\u0010F\u001a\u00020\n*\u00020\n2\f\u0010H\u001a\b\u0012\u0004\u0012\u00020\t0JH\u0086\u0002\u001a\u0015\u0010F\u001a\u00020\f*\u00020\f2\u0006\u0010\u0016\u001a\u00020\u000bH\u0086\u0002\u001a\u0015\u0010F\u001a\u00020\f*\u00020\f2\u0006\u0010H\u001a\u00020\fH\u0086\u0002\u001a\u001b\u0010F\u001a\u00020\f*\u00020\f2\f\u0010H\u001a\b\u0012\u0004\u0012\u00020\u000b0JH\u0086\u0002\u001a\u0015\u0010F\u001a\u00020\u000e*\u00020\u000e2\u0006\u0010\u0016\u001a\u00020\rH\u0086\u0002\u001a\u0015\u0010F\u001a\u00020\u000e*\u00020\u000e2\u0006\u0010H\u001a\u00020\u000eH\u0086\u0002\u001a\u001b\u0010F\u001a\u00020\u000e*\u00020\u000e2\f\u0010H\u001a\b\u0012\u0004\u0012\u00020\r0JH\u0086\u0002\u001a\u0015\u0010F\u001a\u00020\u0010*\u00020\u00102\u0006\u0010\u0016\u001a\u00020\u000fH\u0086\u0002\u001a\u0015\u0010F\u001a\u00020\u0010*\u00020\u00102\u0006\u0010H\u001a\u00020\u0010H\u0086\u0002\u001a\u001b\u0010F\u001a\u00020\u0010*\u00020\u00102\f\u0010H\u001a\b\u0012\u0004\u0012\u00020\u000f0JH\u0086\u0002\u001a\u0015\u0010F\u001a\u00020\u0012*\u00020\u00122\u0006\u0010\u0016\u001a\u00020\u0011H\u0086\u0002\u001a\u0015\u0010F\u001a\u00020\u0012*\u00020\u00122\u0006\u0010H\u001a\u00020\u0012H\u0086\u0002\u001a\u001b\u0010F\u001a\u00020\u0012*\u00020\u00122\f\u0010H\u001a\b\u0012\u0004\u0012\u00020\u00110JH\u0086\u0002\u001a\u0015\u0010F\u001a\u00020\u0014*\u00020\u00142\u0006\u0010\u0016\u001a\u00020\u0013H\u0086\u0002\u001a\u0015\u0010F\u001a\u00020\u0014*\u00020\u00142\u0006\u0010H\u001a\u00020\u0014H\u0086\u0002\u001a\u001b\u0010F\u001a\u00020\u0014*\u00020\u00142\f\u0010H\u001a\b\u0012\u0004\u0012\u00020\u00130JH\u0086\u0002\u001a,\u0010L\u001a\b\u0012\u0004\u0012\u0002H\u00020\u0003\"\u0004\b\u0000\u0010\u0002*\b\u0012\u0004\u0012\u0002H\u00020\u00032\u0006\u0010\u0016\u001a\u0002H\u0002H\u0087\b¢\u0006\u0002\u0010G\u001a\u001d\u0010M\u001a\u00020;\"\u0004\b\u0000\u0010\u0002*\n\u0012\u0006\b\u0001\u0012\u0002H\u00020\u0003¢\u0006\u0002\u0010N\u001a*\u0010M\u001a\u00020;\"\u000e\b\u0000\u0010\u0002*\b\u0012\u0004\u0012\u0002H\u00020O*\n\u0012\u0006\b\u0001\u0012\u0002H\u00020\u0003H\u0087\b¢\u0006\u0002\u0010P\u001a1\u0010M\u001a\u00020;\"\u0004\b\u0000\u0010\u0002*\n\u0012\u0006\b\u0001\u0012\u0002H\u00020\u00032\b\b\u0002\u0010\u001a\u001a\u00020\u000f2\b\b\u0002\u0010\u001b\u001a\u00020\u000f¢\u0006\u0002\u0010Q\u001a\n\u0010M\u001a\u00020;*\u00020\b\u001a\u001e\u0010M\u001a\u00020;*\u00020\b2\b\b\u0002\u0010\u001a\u001a\u00020\u000f2\b\b\u0002\u0010\u001b\u001a\u00020\u000f\u001a\n\u0010M\u001a\u00020;*\u00020\n\u001a\u001e\u0010M\u001a\u00020;*\u00020\n2\b\b\u0002\u0010\u001a\u001a\u00020\u000f2\b\b\u0002\u0010\u001b\u001a\u00020\u000f\u001a\n\u0010M\u001a\u00020;*\u00020\f\u001a\u001e\u0010M\u001a\u00020;*\u00020\f2\b\b\u0002\u0010\u001a\u001a\u00020\u000f2\b\b\u0002\u0010\u001b\u001a\u00020\u000f\u001a\n\u0010M\u001a\u00020;*\u00020\u000e\u001a\u001e\u0010M\u001a\u00020;*\u00020\u000e2\b\b\u0002\u0010\u001a\u001a\u00020\u000f2\b\b\u0002\u0010\u001b\u001a\u00020\u000f\u001a\n\u0010M\u001a\u00020;*\u00020\u0010\u001a\u001e\u0010M\u001a\u00020;*\u00020\u00102\b\b\u0002\u0010\u001a\u001a\u00020\u000f2\b\b\u0002\u0010\u001b\u001a\u00020\u000f\u001a\n\u0010M\u001a\u00020;*\u00020\u0012\u001a\u001e\u0010M\u001a\u00020;*\u00020\u00122\b\b\u0002\u0010\u001a\u001a\u00020\u000f2\b\b\u0002\u0010\u001b\u001a\u00020\u000f\u001a\n\u0010M\u001a\u00020;*\u00020\u0014\u001a\u001e\u0010M\u001a\u00020;*\u00020\u00142\b\b\u0002\u0010\u001a\u001a\u00020\u000f2\b\b\u0002\u0010\u001b\u001a\u00020\u000f\u001a9\u0010R\u001a\u00020;\"\u0004\b\u0000\u0010\u0002*\n\u0012\u0006\b\u0001\u0012\u0002H\u00020\u00032\u001a\u0010\u0017\u001a\u0016\u0012\u0006\b\u0000\u0012\u0002H\u00020\u0018j\n\u0012\u0006\b\u0000\u0012\u0002H\u0002`\u0019¢\u0006\u0002\u0010S\u001aM\u0010R\u001a\u00020;\"\u0004\b\u0000\u0010\u0002*\n\u0012\u0006\b\u0001\u0012\u0002H\u00020\u00032\u001a\u0010\u0017\u001a\u0016\u0012\u0006\b\u0000\u0012\u0002H\u00020\u0018j\n\u0012\u0006\b\u0000\u0012\u0002H\u0002`\u00192\b\b\u0002\u0010\u001a\u001a\u00020\u000f2\b\b\u0002\u0010\u001b\u001a\u00020\u000f¢\u0006\u0002\u0010T\u001a-\u0010U\u001a\b\u0012\u0004\u0012\u0002H\u00020V\"\u000e\b\u0000\u0010\u0002*\b\u0012\u0004\u0012\u0002H\u00020O*\n\u0012\u0006\b\u0001\u0012\u0002H\u00020\u0003¢\u0006\u0002\u0010W\u001a?\u0010U\u001a\b\u0012\u0004\u0012\u0002H\u00020V\"\u0004\b\u0000\u0010\u0002*\n\u0012\u0006\b\u0001\u0012\u0002H\u00020\u00032\u001a\u0010\u0017\u001a\u0016\u0012\u0006\b\u0000\u0012\u0002H\u00020\u0018j\n\u0012\u0006\b\u0000\u0012\u0002H\u0002`\u0019¢\u0006\u0002\u0010X\u001a\u0010\u0010U\u001a\b\u0012\u0004\u0012\u00020\u00050V*\u00020\u0006\u001a\u0010\u0010U\u001a\b\u0012\u0004\u0012\u00020\u00070V*\u00020\b\u001a\u0010\u0010U\u001a\b\u0012\u0004\u0012\u00020\t0V*\u00020\n\u001a\u0010\u0010U\u001a\b\u0012\u0004\u0012\u00020\u000b0V*\u00020\f\u001a\u0010\u0010U\u001a\b\u0012\u0004\u0012\u00020\r0V*\u00020\u000e\u001a\u0010\u0010U\u001a\b\u0012\u0004\u0012\u00020\u000f0V*\u00020\u0010\u001a\u0010\u0010U\u001a\b\u0012\u0004\u0012\u00020\u00110V*\u00020\u0012\u001a\u0010\u0010U\u001a\b\u0012\u0004\u0012\u00020\u00130V*\u00020\u0014\u001a\u0015\u0010Y\u001a\b\u0012\u0004\u0012\u00020\u00050\u0003*\u00020\u0006¢\u0006\u0002\u0010Z\u001a\u0015\u0010Y\u001a\b\u0012\u0004\u0012\u00020\u00070\u0003*\u00020\b¢\u0006\u0002\u0010[\u001a\u0015\u0010Y\u001a\b\u0012\u0004\u0012\u00020\t0\u0003*\u00020\n¢\u0006\u0002\u0010\\\u001a\u0015\u0010Y\u001a\b\u0012\u0004\u0012\u00020\u000b0\u0003*\u00020\f¢\u0006\u0002\u0010]\u001a\u0015\u0010Y\u001a\b\u0012\u0004\u0012\u00020\r0\u0003*\u00020\u000e¢\u0006\u0002\u0010^\u001a\u0015\u0010Y\u001a\b\u0012\u0004\u0012\u00020\u000f0\u0003*\u00020\u0010¢\u0006\u0002\u0010_\u001a\u0015\u0010Y\u001a\b\u0012\u0004\u0012\u00020\u00110\u0003*\u00020\u0012¢\u0006\u0002\u0010`\u001a\u0015\u0010Y\u001a\b\u0012\u0004\u0012\u00020\u00130\u0003*\u00020\u0014¢\u0006\u0002\u0010a¨\u0006b" }, d2 = { "asList", "", "T", "", "([Ljava/lang/Object;)Ljava/util/List;", "", "", "", "", "", "", "", "", "", "", "", "", "", "", "", "", "binarySearch", "element", "comparator", "Ljava/util/Comparator;", "Lkotlin/Comparator;", "fromIndex", "toIndex", "([Ljava/lang/Object;Ljava/lang/Object;Ljava/util/Comparator;II)I", "([Ljava/lang/Object;Ljava/lang/Object;II)I", "contentDeepEquals", "other", "contentDeepEqualsInline", "([Ljava/lang/Object;[Ljava/lang/Object;)Z", "contentDeepHashCode", "contentDeepHashCodeInline", "([Ljava/lang/Object;)I", "contentDeepToString", "", "contentDeepToStringInline", "([Ljava/lang/Object;)Ljava/lang/String;", "contentEquals", "contentHashCode", "contentToString", "copyInto", "destination", "destinationOffset", "startIndex", "endIndex", "([Ljava/lang/Object;[Ljava/lang/Object;III)[Ljava/lang/Object;", "copyOf", "([Ljava/lang/Object;)[Ljava/lang/Object;", "newSize", "([Ljava/lang/Object;I)[Ljava/lang/Object;", "copyOfRange", "copyOfRangeInline", "([Ljava/lang/Object;II)[Ljava/lang/Object;", "copyOfRangeImpl", "fill", "", "([Ljava/lang/Object;Ljava/lang/Object;II)V", "filterIsInstance", "R", "klass", "Ljava/lang/Class;", "([Ljava/lang/Object;Ljava/lang/Class;)Ljava/util/List;", "filterIsInstanceTo", "C", "", "([Ljava/lang/Object;Ljava/util/Collection;Ljava/lang/Class;)Ljava/util/Collection;", "plus", "([Ljava/lang/Object;Ljava/lang/Object;)[Ljava/lang/Object;", "elements", "([Ljava/lang/Object;[Ljava/lang/Object;)[Ljava/lang/Object;", "", "([Ljava/lang/Object;Ljava/util/Collection;)[Ljava/lang/Object;", "plusElement", "sort", "([Ljava/lang/Object;)V", "", "([Ljava/lang/Comparable;)V", "([Ljava/lang/Object;II)V", "sortWith", "([Ljava/lang/Object;Ljava/util/Comparator;)V", "([Ljava/lang/Object;Ljava/util/Comparator;II)V", "toSortedSet", "Ljava/util/SortedSet;", "([Ljava/lang/Comparable;)Ljava/util/SortedSet;", "([Ljava/lang/Object;Ljava/util/Comparator;)Ljava/util/SortedSet;", "toTypedArray", "([Z)[Ljava/lang/Boolean;", "([B)[Ljava/lang/Byte;", "([C)[Ljava/lang/Character;", "([D)[Ljava/lang/Double;", "([F)[Ljava/lang/Float;", "([I)[Ljava/lang/Integer;", "([J)[Ljava/lang/Long;", "([S)[Ljava/lang/Short;", "kotlin-stdlib" }, xs = "kotlin/collections/ArraysKt")
class ArraysKt___ArraysJvmKt extends ArraysKt__ArraysKt
{
    @NotNull
    public static final <R> List<R> filterIsInstance(@NotNull final Object[] $receiver, @NotNull final Class<R> klass) {
        Intrinsics.checkParameterIsNotNull($receiver, "receiver$0");
        Intrinsics.checkParameterIsNotNull(klass, "klass");
        return filterIsInstanceTo($receiver, new ArrayList<R>(), klass);
    }
    
    @NotNull
    public static final <C extends Collection<? super R>, R> C filterIsInstanceTo(@NotNull final Object[] $receiver, @NotNull final C destination, @NotNull final Class<R> klass) {
        Intrinsics.checkParameterIsNotNull($receiver, "receiver$0");
        Intrinsics.checkParameterIsNotNull(destination, "destination");
        Intrinsics.checkParameterIsNotNull(klass, "klass");
        for (final Object element : $receiver) {
            if (klass.isInstance(element)) {
                destination.add((Object)element);
            }
        }
        return destination;
    }
    
    @NotNull
    public static final <T> List<T> asList(@NotNull final T[] $receiver) {
        Intrinsics.checkParameterIsNotNull($receiver, "receiver$0");
        final List<T> list = ArraysUtilJVM.asList($receiver);
        Intrinsics.checkExpressionValueIsNotNull(list, "ArraysUtilJVM.asList(this)");
        return list;
    }
    
    @NotNull
    public static final List<Byte> asList(@NotNull final byte[] $receiver) {
        Intrinsics.checkParameterIsNotNull($receiver, "receiver$0");
        return (List<Byte>)new ArraysKt___ArraysJvmKt$asList.ArraysKt___ArraysJvmKt$asList$1($receiver);
    }
    
    @NotNull
    public static final List<Short> asList(@NotNull final short[] $receiver) {
        Intrinsics.checkParameterIsNotNull($receiver, "receiver$0");
        return (List<Short>)new ArraysKt___ArraysJvmKt$asList.ArraysKt___ArraysJvmKt$asList$2($receiver);
    }
    
    @NotNull
    public static final List<Integer> asList(@NotNull final int[] $receiver) {
        Intrinsics.checkParameterIsNotNull($receiver, "receiver$0");
        return (List<Integer>)new ArraysKt___ArraysJvmKt$asList.ArraysKt___ArraysJvmKt$asList$3($receiver);
    }
    
    @NotNull
    public static final List<Long> asList(@NotNull final long[] $receiver) {
        Intrinsics.checkParameterIsNotNull($receiver, "receiver$0");
        return (List<Long>)new ArraysKt___ArraysJvmKt$asList.ArraysKt___ArraysJvmKt$asList$4($receiver);
    }
    
    @NotNull
    public static final List<Float> asList(@NotNull final float[] $receiver) {
        Intrinsics.checkParameterIsNotNull($receiver, "receiver$0");
        return (List<Float>)new ArraysKt___ArraysJvmKt$asList.ArraysKt___ArraysJvmKt$asList$5($receiver);
    }
    
    @NotNull
    public static final List<Double> asList(@NotNull final double[] $receiver) {
        Intrinsics.checkParameterIsNotNull($receiver, "receiver$0");
        return (List<Double>)new ArraysKt___ArraysJvmKt$asList.ArraysKt___ArraysJvmKt$asList$6($receiver);
    }
    
    @NotNull
    public static final List<Boolean> asList(@NotNull final boolean[] $receiver) {
        Intrinsics.checkParameterIsNotNull($receiver, "receiver$0");
        return (List<Boolean>)new ArraysKt___ArraysJvmKt$asList.ArraysKt___ArraysJvmKt$asList$7($receiver);
    }
    
    @NotNull
    public static final List<Character> asList(@NotNull final char[] $receiver) {
        Intrinsics.checkParameterIsNotNull($receiver, "receiver$0");
        return (List<Character>)new ArraysKt___ArraysJvmKt$asList.ArraysKt___ArraysJvmKt$asList$8($receiver);
    }
    
    public static final <T> int binarySearch(@NotNull final T[] $receiver, final T element, @NotNull final Comparator<? super T> comparator, final int fromIndex, final int toIndex) {
        Intrinsics.checkParameterIsNotNull($receiver, "receiver$0");
        Intrinsics.checkParameterIsNotNull(comparator, "comparator");
        return Arrays.binarySearch($receiver, fromIndex, toIndex, element, comparator);
    }
    
    public static final <T> int binarySearch(@NotNull final T[] $receiver, final T element, final int fromIndex, final int toIndex) {
        Intrinsics.checkParameterIsNotNull($receiver, "receiver$0");
        return Arrays.binarySearch($receiver, fromIndex, toIndex, element);
    }
    
    public static final int binarySearch(@NotNull final byte[] $receiver, final byte element, final int fromIndex, final int toIndex) {
        Intrinsics.checkParameterIsNotNull($receiver, "receiver$0");
        return Arrays.binarySearch($receiver, fromIndex, toIndex, element);
    }
    
    public static final int binarySearch(@NotNull final short[] $receiver, final short element, final int fromIndex, final int toIndex) {
        Intrinsics.checkParameterIsNotNull($receiver, "receiver$0");
        return Arrays.binarySearch($receiver, fromIndex, toIndex, element);
    }
    
    public static final int binarySearch(@NotNull final int[] $receiver, final int element, final int fromIndex, final int toIndex) {
        Intrinsics.checkParameterIsNotNull($receiver, "receiver$0");
        return Arrays.binarySearch($receiver, fromIndex, toIndex, element);
    }
    
    public static final int binarySearch(@NotNull final long[] $receiver, final long element, final int fromIndex, final int toIndex) {
        Intrinsics.checkParameterIsNotNull($receiver, "receiver$0");
        return Arrays.binarySearch($receiver, fromIndex, toIndex, element);
    }
    
    public static final int binarySearch(@NotNull final float[] $receiver, final float element, final int fromIndex, final int toIndex) {
        Intrinsics.checkParameterIsNotNull($receiver, "receiver$0");
        return Arrays.binarySearch($receiver, fromIndex, toIndex, element);
    }
    
    public static final int binarySearch(@NotNull final double[] $receiver, final double element, final int fromIndex, final int toIndex) {
        Intrinsics.checkParameterIsNotNull($receiver, "receiver$0");
        return Arrays.binarySearch($receiver, fromIndex, toIndex, element);
    }
    
    public static final int binarySearch(@NotNull final char[] $receiver, final char element, final int fromIndex, final int toIndex) {
        Intrinsics.checkParameterIsNotNull($receiver, "receiver$0");
        return Arrays.binarySearch($receiver, fromIndex, toIndex, element);
    }
    
    @SinceKotlin(version = "1.1")
    @JvmName(name = "contentDeepEqualsInline")
    @InlineOnly
    private static final <T> boolean contentDeepEqualsInline(@NotNull final T[] $receiver, final T[] other) {
        if (PlatformImplementationsKt.apiVersionIsAtLeast(1, 3, 0)) {
            return ArraysKt__ArraysKt.contentDeepEquals($receiver, other);
        }
        return Arrays.deepEquals($receiver, other);
    }
    
    @SinceKotlin(version = "1.1")
    @JvmName(name = "contentDeepHashCodeInline")
    @InlineOnly
    private static final <T> int contentDeepHashCodeInline(@NotNull final T[] $receiver) {
        if (PlatformImplementationsKt.apiVersionIsAtLeast(1, 3, 0)) {
            return ArraysKt__ArraysJVMKt.contentDeepHashCode($receiver);
        }
        return Arrays.deepHashCode($receiver);
    }
    
    @SinceKotlin(version = "1.1")
    @JvmName(name = "contentDeepToStringInline")
    @InlineOnly
    private static final <T> String contentDeepToStringInline(@NotNull final T[] $receiver) {
        if (PlatformImplementationsKt.apiVersionIsAtLeast(1, 3, 0)) {
            return ArraysKt__ArraysKt.contentDeepToString($receiver);
        }
        final String deepToString = Arrays.deepToString($receiver);
        Intrinsics.checkExpressionValueIsNotNull(deepToString, "java.util.Arrays.deepToString(this)");
        return deepToString;
    }
    
    @SinceKotlin(version = "1.1")
    @InlineOnly
    private static final <T> boolean contentEquals(@NotNull final T[] $receiver, final T[] other) {
        return Arrays.equals($receiver, other);
    }
    
    @SinceKotlin(version = "1.1")
    @InlineOnly
    private static final boolean contentEquals(@NotNull final byte[] $receiver, final byte[] other) {
        return Arrays.equals($receiver, other);
    }
    
    @SinceKotlin(version = "1.1")
    @InlineOnly
    private static final boolean contentEquals(@NotNull final short[] $receiver, final short[] other) {
        return Arrays.equals($receiver, other);
    }
    
    @SinceKotlin(version = "1.1")
    @InlineOnly
    private static final boolean contentEquals(@NotNull final int[] $receiver, final int[] other) {
        return Arrays.equals($receiver, other);
    }
    
    @SinceKotlin(version = "1.1")
    @InlineOnly
    private static final boolean contentEquals(@NotNull final long[] $receiver, final long[] other) {
        return Arrays.equals($receiver, other);
    }
    
    @SinceKotlin(version = "1.1")
    @InlineOnly
    private static final boolean contentEquals(@NotNull final float[] $receiver, final float[] other) {
        return Arrays.equals($receiver, other);
    }
    
    @SinceKotlin(version = "1.1")
    @InlineOnly
    private static final boolean contentEquals(@NotNull final double[] $receiver, final double[] other) {
        return Arrays.equals($receiver, other);
    }
    
    @SinceKotlin(version = "1.1")
    @InlineOnly
    private static final boolean contentEquals(@NotNull final boolean[] $receiver, final boolean[] other) {
        return Arrays.equals($receiver, other);
    }
    
    @SinceKotlin(version = "1.1")
    @InlineOnly
    private static final boolean contentEquals(@NotNull final char[] $receiver, final char[] other) {
        return Arrays.equals($receiver, other);
    }
    
    @SinceKotlin(version = "1.1")
    @InlineOnly
    private static final <T> int contentHashCode(@NotNull final T[] $receiver) {
        return Arrays.hashCode($receiver);
    }
    
    @SinceKotlin(version = "1.1")
    @InlineOnly
    private static final int contentHashCode(@NotNull final byte[] $receiver) {
        return Arrays.hashCode($receiver);
    }
    
    @SinceKotlin(version = "1.1")
    @InlineOnly
    private static final int contentHashCode(@NotNull final short[] $receiver) {
        return Arrays.hashCode($receiver);
    }
    
    @SinceKotlin(version = "1.1")
    @InlineOnly
    private static final int contentHashCode(@NotNull final int[] $receiver) {
        return Arrays.hashCode($receiver);
    }
    
    @SinceKotlin(version = "1.1")
    @InlineOnly
    private static final int contentHashCode(@NotNull final long[] $receiver) {
        return Arrays.hashCode($receiver);
    }
    
    @SinceKotlin(version = "1.1")
    @InlineOnly
    private static final int contentHashCode(@NotNull final float[] $receiver) {
        return Arrays.hashCode($receiver);
    }
    
    @SinceKotlin(version = "1.1")
    @InlineOnly
    private static final int contentHashCode(@NotNull final double[] $receiver) {
        return Arrays.hashCode($receiver);
    }
    
    @SinceKotlin(version = "1.1")
    @InlineOnly
    private static final int contentHashCode(@NotNull final boolean[] $receiver) {
        return Arrays.hashCode($receiver);
    }
    
    @SinceKotlin(version = "1.1")
    @InlineOnly
    private static final int contentHashCode(@NotNull final char[] $receiver) {
        return Arrays.hashCode($receiver);
    }
    
    @SinceKotlin(version = "1.1")
    @InlineOnly
    private static final <T> String contentToString(@NotNull final T[] $receiver) {
        final String string = Arrays.toString($receiver);
        Intrinsics.checkExpressionValueIsNotNull(string, "java.util.Arrays.toString(this)");
        return string;
    }
    
    @SinceKotlin(version = "1.1")
    @InlineOnly
    private static final String contentToString(@NotNull final byte[] $receiver) {
        final String string = Arrays.toString($receiver);
        Intrinsics.checkExpressionValueIsNotNull(string, "java.util.Arrays.toString(this)");
        return string;
    }
    
    @SinceKotlin(version = "1.1")
    @InlineOnly
    private static final String contentToString(@NotNull final short[] $receiver) {
        final String string = Arrays.toString($receiver);
        Intrinsics.checkExpressionValueIsNotNull(string, "java.util.Arrays.toString(this)");
        return string;
    }
    
    @SinceKotlin(version = "1.1")
    @InlineOnly
    private static final String contentToString(@NotNull final int[] $receiver) {
        final String string = Arrays.toString($receiver);
        Intrinsics.checkExpressionValueIsNotNull(string, "java.util.Arrays.toString(this)");
        return string;
    }
    
    @SinceKotlin(version = "1.1")
    @InlineOnly
    private static final String contentToString(@NotNull final long[] $receiver) {
        final String string = Arrays.toString($receiver);
        Intrinsics.checkExpressionValueIsNotNull(string, "java.util.Arrays.toString(this)");
        return string;
    }
    
    @SinceKotlin(version = "1.1")
    @InlineOnly
    private static final String contentToString(@NotNull final float[] $receiver) {
        final String string = Arrays.toString($receiver);
        Intrinsics.checkExpressionValueIsNotNull(string, "java.util.Arrays.toString(this)");
        return string;
    }
    
    @SinceKotlin(version = "1.1")
    @InlineOnly
    private static final String contentToString(@NotNull final double[] $receiver) {
        final String string = Arrays.toString($receiver);
        Intrinsics.checkExpressionValueIsNotNull(string, "java.util.Arrays.toString(this)");
        return string;
    }
    
    @SinceKotlin(version = "1.1")
    @InlineOnly
    private static final String contentToString(@NotNull final boolean[] $receiver) {
        final String string = Arrays.toString($receiver);
        Intrinsics.checkExpressionValueIsNotNull(string, "java.util.Arrays.toString(this)");
        return string;
    }
    
    @SinceKotlin(version = "1.1")
    @InlineOnly
    private static final String contentToString(@NotNull final char[] $receiver) {
        final String string = Arrays.toString($receiver);
        Intrinsics.checkExpressionValueIsNotNull(string, "java.util.Arrays.toString(this)");
        return string;
    }
    
    @SinceKotlin(version = "1.3")
    @NotNull
    public static final <T> T[] copyInto(@NotNull final T[] $receiver, @NotNull final T[] destination, final int destinationOffset, final int startIndex, final int endIndex) {
        Intrinsics.checkParameterIsNotNull($receiver, "receiver$0");
        Intrinsics.checkParameterIsNotNull(destination, "destination");
        System.arraycopy($receiver, startIndex, destination, destinationOffset, endIndex - startIndex);
        return destination;
    }
    
    @SinceKotlin(version = "1.3")
    @NotNull
    public static final byte[] copyInto(@NotNull final byte[] $receiver, @NotNull final byte[] destination, final int destinationOffset, final int startIndex, final int endIndex) {
        Intrinsics.checkParameterIsNotNull($receiver, "receiver$0");
        Intrinsics.checkParameterIsNotNull(destination, "destination");
        System.arraycopy($receiver, startIndex, destination, destinationOffset, endIndex - startIndex);
        return destination;
    }
    
    @SinceKotlin(version = "1.3")
    @NotNull
    public static final short[] copyInto(@NotNull final short[] $receiver, @NotNull final short[] destination, final int destinationOffset, final int startIndex, final int endIndex) {
        Intrinsics.checkParameterIsNotNull($receiver, "receiver$0");
        Intrinsics.checkParameterIsNotNull(destination, "destination");
        System.arraycopy($receiver, startIndex, destination, destinationOffset, endIndex - startIndex);
        return destination;
    }
    
    @SinceKotlin(version = "1.3")
    @NotNull
    public static final int[] copyInto(@NotNull final int[] $receiver, @NotNull final int[] destination, final int destinationOffset, final int startIndex, final int endIndex) {
        Intrinsics.checkParameterIsNotNull($receiver, "receiver$0");
        Intrinsics.checkParameterIsNotNull(destination, "destination");
        System.arraycopy($receiver, startIndex, destination, destinationOffset, endIndex - startIndex);
        return destination;
    }
    
    @SinceKotlin(version = "1.3")
    @NotNull
    public static final long[] copyInto(@NotNull final long[] $receiver, @NotNull final long[] destination, final int destinationOffset, final int startIndex, final int endIndex) {
        Intrinsics.checkParameterIsNotNull($receiver, "receiver$0");
        Intrinsics.checkParameterIsNotNull(destination, "destination");
        System.arraycopy($receiver, startIndex, destination, destinationOffset, endIndex - startIndex);
        return destination;
    }
    
    @SinceKotlin(version = "1.3")
    @NotNull
    public static final float[] copyInto(@NotNull final float[] $receiver, @NotNull final float[] destination, final int destinationOffset, final int startIndex, final int endIndex) {
        Intrinsics.checkParameterIsNotNull($receiver, "receiver$0");
        Intrinsics.checkParameterIsNotNull(destination, "destination");
        System.arraycopy($receiver, startIndex, destination, destinationOffset, endIndex - startIndex);
        return destination;
    }
    
    @SinceKotlin(version = "1.3")
    @NotNull
    public static final double[] copyInto(@NotNull final double[] $receiver, @NotNull final double[] destination, final int destinationOffset, final int startIndex, final int endIndex) {
        Intrinsics.checkParameterIsNotNull($receiver, "receiver$0");
        Intrinsics.checkParameterIsNotNull(destination, "destination");
        System.arraycopy($receiver, startIndex, destination, destinationOffset, endIndex - startIndex);
        return destination;
    }
    
    @SinceKotlin(version = "1.3")
    @NotNull
    public static final boolean[] copyInto(@NotNull final boolean[] $receiver, @NotNull final boolean[] destination, final int destinationOffset, final int startIndex, final int endIndex) {
        Intrinsics.checkParameterIsNotNull($receiver, "receiver$0");
        Intrinsics.checkParameterIsNotNull(destination, "destination");
        System.arraycopy($receiver, startIndex, destination, destinationOffset, endIndex - startIndex);
        return destination;
    }
    
    @SinceKotlin(version = "1.3")
    @NotNull
    public static final char[] copyInto(@NotNull final char[] $receiver, @NotNull final char[] destination, final int destinationOffset, final int startIndex, final int endIndex) {
        Intrinsics.checkParameterIsNotNull($receiver, "receiver$0");
        Intrinsics.checkParameterIsNotNull(destination, "destination");
        System.arraycopy($receiver, startIndex, destination, destinationOffset, endIndex - startIndex);
        return destination;
    }
    
    @InlineOnly
    private static final <T> T[] copyOf(@NotNull final T[] $receiver) {
        final T[] copy = Arrays.copyOf($receiver, $receiver.length);
        Intrinsics.checkExpressionValueIsNotNull(copy, "java.util.Arrays.copyOf(this, size)");
        return copy;
    }
    
    @InlineOnly
    private static final byte[] copyOf(@NotNull final byte[] $receiver) {
        final byte[] copy = Arrays.copyOf($receiver, $receiver.length);
        Intrinsics.checkExpressionValueIsNotNull(copy, "java.util.Arrays.copyOf(this, size)");
        return copy;
    }
    
    @InlineOnly
    private static final short[] copyOf(@NotNull final short[] $receiver) {
        final short[] copy = Arrays.copyOf($receiver, $receiver.length);
        Intrinsics.checkExpressionValueIsNotNull(copy, "java.util.Arrays.copyOf(this, size)");
        return copy;
    }
    
    @InlineOnly
    private static final int[] copyOf(@NotNull final int[] $receiver) {
        final int[] copy = Arrays.copyOf($receiver, $receiver.length);
        Intrinsics.checkExpressionValueIsNotNull(copy, "java.util.Arrays.copyOf(this, size)");
        return copy;
    }
    
    @InlineOnly
    private static final long[] copyOf(@NotNull final long[] $receiver) {
        final long[] copy = Arrays.copyOf($receiver, $receiver.length);
        Intrinsics.checkExpressionValueIsNotNull(copy, "java.util.Arrays.copyOf(this, size)");
        return copy;
    }
    
    @InlineOnly
    private static final float[] copyOf(@NotNull final float[] $receiver) {
        final float[] copy = Arrays.copyOf($receiver, $receiver.length);
        Intrinsics.checkExpressionValueIsNotNull(copy, "java.util.Arrays.copyOf(this, size)");
        return copy;
    }
    
    @InlineOnly
    private static final double[] copyOf(@NotNull final double[] $receiver) {
        final double[] copy = Arrays.copyOf($receiver, $receiver.length);
        Intrinsics.checkExpressionValueIsNotNull(copy, "java.util.Arrays.copyOf(this, size)");
        return copy;
    }
    
    @InlineOnly
    private static final boolean[] copyOf(@NotNull final boolean[] $receiver) {
        final boolean[] copy = Arrays.copyOf($receiver, $receiver.length);
        Intrinsics.checkExpressionValueIsNotNull(copy, "java.util.Arrays.copyOf(this, size)");
        return copy;
    }
    
    @InlineOnly
    private static final char[] copyOf(@NotNull final char[] $receiver) {
        final char[] copy = Arrays.copyOf($receiver, $receiver.length);
        Intrinsics.checkExpressionValueIsNotNull(copy, "java.util.Arrays.copyOf(this, size)");
        return copy;
    }
    
    @InlineOnly
    private static final byte[] copyOf(@NotNull final byte[] $receiver, final int newSize) {
        final byte[] copy = Arrays.copyOf($receiver, newSize);
        Intrinsics.checkExpressionValueIsNotNull(copy, "java.util.Arrays.copyOf(this, newSize)");
        return copy;
    }
    
    @InlineOnly
    private static final short[] copyOf(@NotNull final short[] $receiver, final int newSize) {
        final short[] copy = Arrays.copyOf($receiver, newSize);
        Intrinsics.checkExpressionValueIsNotNull(copy, "java.util.Arrays.copyOf(this, newSize)");
        return copy;
    }
    
    @InlineOnly
    private static final int[] copyOf(@NotNull final int[] $receiver, final int newSize) {
        final int[] copy = Arrays.copyOf($receiver, newSize);
        Intrinsics.checkExpressionValueIsNotNull(copy, "java.util.Arrays.copyOf(this, newSize)");
        return copy;
    }
    
    @InlineOnly
    private static final long[] copyOf(@NotNull final long[] $receiver, final int newSize) {
        final long[] copy = Arrays.copyOf($receiver, newSize);
        Intrinsics.checkExpressionValueIsNotNull(copy, "java.util.Arrays.copyOf(this, newSize)");
        return copy;
    }
    
    @InlineOnly
    private static final float[] copyOf(@NotNull final float[] $receiver, final int newSize) {
        final float[] copy = Arrays.copyOf($receiver, newSize);
        Intrinsics.checkExpressionValueIsNotNull(copy, "java.util.Arrays.copyOf(this, newSize)");
        return copy;
    }
    
    @InlineOnly
    private static final double[] copyOf(@NotNull final double[] $receiver, final int newSize) {
        final double[] copy = Arrays.copyOf($receiver, newSize);
        Intrinsics.checkExpressionValueIsNotNull(copy, "java.util.Arrays.copyOf(this, newSize)");
        return copy;
    }
    
    @InlineOnly
    private static final boolean[] copyOf(@NotNull final boolean[] $receiver, final int newSize) {
        final boolean[] copy = Arrays.copyOf($receiver, newSize);
        Intrinsics.checkExpressionValueIsNotNull(copy, "java.util.Arrays.copyOf(this, newSize)");
        return copy;
    }
    
    @InlineOnly
    private static final char[] copyOf(@NotNull final char[] $receiver, final int newSize) {
        final char[] copy = Arrays.copyOf($receiver, newSize);
        Intrinsics.checkExpressionValueIsNotNull(copy, "java.util.Arrays.copyOf(this, newSize)");
        return copy;
    }
    
    @InlineOnly
    private static final <T> T[] copyOf(@NotNull final T[] $receiver, final int newSize) {
        final T[] copy = Arrays.copyOf($receiver, newSize);
        Intrinsics.checkExpressionValueIsNotNull(copy, "java.util.Arrays.copyOf(this, newSize)");
        return copy;
    }
    
    @JvmName(name = "copyOfRangeInline")
    @InlineOnly
    private static final <T> T[] copyOfRangeInline(@NotNull final T[] $receiver, final int fromIndex, final int toIndex) {
        Object[] array;
        if (PlatformImplementationsKt.apiVersionIsAtLeast(1, 3, 0)) {
            array = copyOfRange((Object[])$receiver, fromIndex, toIndex);
        }
        else {
            if (toIndex > $receiver.length) {
                throw new IndexOutOfBoundsException("toIndex: " + toIndex + ", size: " + $receiver.length);
            }
            Intrinsics.checkExpressionValueIsNotNull(array = Arrays.copyOfRange($receiver, fromIndex, toIndex), "java.util.Arrays.copyOfR\u2026this, fromIndex, toIndex)");
        }
        return (T[])array;
    }
    
    @JvmName(name = "copyOfRangeInline")
    @InlineOnly
    private static final byte[] copyOfRangeInline(@NotNull final byte[] $receiver, final int fromIndex, final int toIndex) {
        byte[] array;
        if (PlatformImplementationsKt.apiVersionIsAtLeast(1, 3, 0)) {
            array = copyOfRange($receiver, fromIndex, toIndex);
        }
        else {
            if (toIndex > $receiver.length) {
                throw new IndexOutOfBoundsException("toIndex: " + toIndex + ", size: " + $receiver.length);
            }
            Intrinsics.checkExpressionValueIsNotNull(array = Arrays.copyOfRange($receiver, fromIndex, toIndex), "java.util.Arrays.copyOfR\u2026this, fromIndex, toIndex)");
        }
        return array;
    }
    
    @JvmName(name = "copyOfRangeInline")
    @InlineOnly
    private static final short[] copyOfRangeInline(@NotNull final short[] $receiver, final int fromIndex, final int toIndex) {
        short[] array;
        if (PlatformImplementationsKt.apiVersionIsAtLeast(1, 3, 0)) {
            array = copyOfRange($receiver, fromIndex, toIndex);
        }
        else {
            if (toIndex > $receiver.length) {
                throw new IndexOutOfBoundsException("toIndex: " + toIndex + ", size: " + $receiver.length);
            }
            Intrinsics.checkExpressionValueIsNotNull(array = Arrays.copyOfRange($receiver, fromIndex, toIndex), "java.util.Arrays.copyOfR\u2026this, fromIndex, toIndex)");
        }
        return array;
    }
    
    @JvmName(name = "copyOfRangeInline")
    @InlineOnly
    private static final int[] copyOfRangeInline(@NotNull final int[] $receiver, final int fromIndex, final int toIndex) {
        int[] array;
        if (PlatformImplementationsKt.apiVersionIsAtLeast(1, 3, 0)) {
            array = copyOfRange($receiver, fromIndex, toIndex);
        }
        else {
            if (toIndex > $receiver.length) {
                throw new IndexOutOfBoundsException("toIndex: " + toIndex + ", size: " + $receiver.length);
            }
            Intrinsics.checkExpressionValueIsNotNull(array = Arrays.copyOfRange($receiver, fromIndex, toIndex), "java.util.Arrays.copyOfR\u2026this, fromIndex, toIndex)");
        }
        return array;
    }
    
    @JvmName(name = "copyOfRangeInline")
    @InlineOnly
    private static final long[] copyOfRangeInline(@NotNull final long[] $receiver, final int fromIndex, final int toIndex) {
        long[] array;
        if (PlatformImplementationsKt.apiVersionIsAtLeast(1, 3, 0)) {
            array = copyOfRange($receiver, fromIndex, toIndex);
        }
        else {
            if (toIndex > $receiver.length) {
                throw new IndexOutOfBoundsException("toIndex: " + toIndex + ", size: " + $receiver.length);
            }
            Intrinsics.checkExpressionValueIsNotNull(array = Arrays.copyOfRange($receiver, fromIndex, toIndex), "java.util.Arrays.copyOfR\u2026this, fromIndex, toIndex)");
        }
        return array;
    }
    
    @JvmName(name = "copyOfRangeInline")
    @InlineOnly
    private static final float[] copyOfRangeInline(@NotNull final float[] $receiver, final int fromIndex, final int toIndex) {
        float[] array;
        if (PlatformImplementationsKt.apiVersionIsAtLeast(1, 3, 0)) {
            array = copyOfRange($receiver, fromIndex, toIndex);
        }
        else {
            if (toIndex > $receiver.length) {
                throw new IndexOutOfBoundsException("toIndex: " + toIndex + ", size: " + $receiver.length);
            }
            Intrinsics.checkExpressionValueIsNotNull(array = Arrays.copyOfRange($receiver, fromIndex, toIndex), "java.util.Arrays.copyOfR\u2026this, fromIndex, toIndex)");
        }
        return array;
    }
    
    @JvmName(name = "copyOfRangeInline")
    @InlineOnly
    private static final double[] copyOfRangeInline(@NotNull final double[] $receiver, final int fromIndex, final int toIndex) {
        double[] array;
        if (PlatformImplementationsKt.apiVersionIsAtLeast(1, 3, 0)) {
            array = copyOfRange($receiver, fromIndex, toIndex);
        }
        else {
            if (toIndex > $receiver.length) {
                throw new IndexOutOfBoundsException("toIndex: " + toIndex + ", size: " + $receiver.length);
            }
            Intrinsics.checkExpressionValueIsNotNull(array = Arrays.copyOfRange($receiver, fromIndex, toIndex), "java.util.Arrays.copyOfR\u2026this, fromIndex, toIndex)");
        }
        return array;
    }
    
    @JvmName(name = "copyOfRangeInline")
    @InlineOnly
    private static final boolean[] copyOfRangeInline(@NotNull final boolean[] $receiver, final int fromIndex, final int toIndex) {
        boolean[] array;
        if (PlatformImplementationsKt.apiVersionIsAtLeast(1, 3, 0)) {
            array = copyOfRange($receiver, fromIndex, toIndex);
        }
        else {
            if (toIndex > $receiver.length) {
                throw new IndexOutOfBoundsException("toIndex: " + toIndex + ", size: " + $receiver.length);
            }
            Intrinsics.checkExpressionValueIsNotNull(array = Arrays.copyOfRange($receiver, fromIndex, toIndex), "java.util.Arrays.copyOfR\u2026this, fromIndex, toIndex)");
        }
        return array;
    }
    
    @JvmName(name = "copyOfRangeInline")
    @InlineOnly
    private static final char[] copyOfRangeInline(@NotNull final char[] $receiver, final int fromIndex, final int toIndex) {
        char[] array;
        if (PlatformImplementationsKt.apiVersionIsAtLeast(1, 3, 0)) {
            array = copyOfRange($receiver, fromIndex, toIndex);
        }
        else {
            if (toIndex > $receiver.length) {
                throw new IndexOutOfBoundsException("toIndex: " + toIndex + ", size: " + $receiver.length);
            }
            Intrinsics.checkExpressionValueIsNotNull(array = Arrays.copyOfRange($receiver, fromIndex, toIndex), "java.util.Arrays.copyOfR\u2026this, fromIndex, toIndex)");
        }
        return array;
    }
    
    @SinceKotlin(version = "1.3")
    @PublishedApi
    @JvmName(name = "copyOfRange")
    @NotNull
    public static final <T> T[] copyOfRange(@NotNull final T[] $receiver, final int fromIndex, final int toIndex) {
        Intrinsics.checkParameterIsNotNull($receiver, "receiver$0");
        ArraysKt__ArraysJVMKt.copyOfRangeToIndexCheck(toIndex, $receiver.length);
        final T[] copyOfRange = Arrays.copyOfRange($receiver, fromIndex, toIndex);
        Intrinsics.checkExpressionValueIsNotNull(copyOfRange, "java.util.Arrays.copyOfR\u2026this, fromIndex, toIndex)");
        return copyOfRange;
    }
    
    @SinceKotlin(version = "1.3")
    @PublishedApi
    @JvmName(name = "copyOfRange")
    @NotNull
    public static final byte[] copyOfRange(@NotNull final byte[] $receiver, final int fromIndex, final int toIndex) {
        Intrinsics.checkParameterIsNotNull($receiver, "receiver$0");
        ArraysKt__ArraysJVMKt.copyOfRangeToIndexCheck(toIndex, $receiver.length);
        final byte[] copyOfRange = Arrays.copyOfRange($receiver, fromIndex, toIndex);
        Intrinsics.checkExpressionValueIsNotNull(copyOfRange, "java.util.Arrays.copyOfR\u2026this, fromIndex, toIndex)");
        return copyOfRange;
    }
    
    @SinceKotlin(version = "1.3")
    @PublishedApi
    @JvmName(name = "copyOfRange")
    @NotNull
    public static final short[] copyOfRange(@NotNull final short[] $receiver, final int fromIndex, final int toIndex) {
        Intrinsics.checkParameterIsNotNull($receiver, "receiver$0");
        ArraysKt__ArraysJVMKt.copyOfRangeToIndexCheck(toIndex, $receiver.length);
        final short[] copyOfRange = Arrays.copyOfRange($receiver, fromIndex, toIndex);
        Intrinsics.checkExpressionValueIsNotNull(copyOfRange, "java.util.Arrays.copyOfR\u2026this, fromIndex, toIndex)");
        return copyOfRange;
    }
    
    @SinceKotlin(version = "1.3")
    @PublishedApi
    @JvmName(name = "copyOfRange")
    @NotNull
    public static final int[] copyOfRange(@NotNull final int[] $receiver, final int fromIndex, final int toIndex) {
        Intrinsics.checkParameterIsNotNull($receiver, "receiver$0");
        ArraysKt__ArraysJVMKt.copyOfRangeToIndexCheck(toIndex, $receiver.length);
        final int[] copyOfRange = Arrays.copyOfRange($receiver, fromIndex, toIndex);
        Intrinsics.checkExpressionValueIsNotNull(copyOfRange, "java.util.Arrays.copyOfR\u2026this, fromIndex, toIndex)");
        return copyOfRange;
    }
    
    @SinceKotlin(version = "1.3")
    @PublishedApi
    @JvmName(name = "copyOfRange")
    @NotNull
    public static final long[] copyOfRange(@NotNull final long[] $receiver, final int fromIndex, final int toIndex) {
        Intrinsics.checkParameterIsNotNull($receiver, "receiver$0");
        ArraysKt__ArraysJVMKt.copyOfRangeToIndexCheck(toIndex, $receiver.length);
        final long[] copyOfRange = Arrays.copyOfRange($receiver, fromIndex, toIndex);
        Intrinsics.checkExpressionValueIsNotNull(copyOfRange, "java.util.Arrays.copyOfR\u2026this, fromIndex, toIndex)");
        return copyOfRange;
    }
    
    @SinceKotlin(version = "1.3")
    @PublishedApi
    @JvmName(name = "copyOfRange")
    @NotNull
    public static final float[] copyOfRange(@NotNull final float[] $receiver, final int fromIndex, final int toIndex) {
        Intrinsics.checkParameterIsNotNull($receiver, "receiver$0");
        ArraysKt__ArraysJVMKt.copyOfRangeToIndexCheck(toIndex, $receiver.length);
        final float[] copyOfRange = Arrays.copyOfRange($receiver, fromIndex, toIndex);
        Intrinsics.checkExpressionValueIsNotNull(copyOfRange, "java.util.Arrays.copyOfR\u2026this, fromIndex, toIndex)");
        return copyOfRange;
    }
    
    @SinceKotlin(version = "1.3")
    @PublishedApi
    @JvmName(name = "copyOfRange")
    @NotNull
    public static final double[] copyOfRange(@NotNull final double[] $receiver, final int fromIndex, final int toIndex) {
        Intrinsics.checkParameterIsNotNull($receiver, "receiver$0");
        ArraysKt__ArraysJVMKt.copyOfRangeToIndexCheck(toIndex, $receiver.length);
        final double[] copyOfRange = Arrays.copyOfRange($receiver, fromIndex, toIndex);
        Intrinsics.checkExpressionValueIsNotNull(copyOfRange, "java.util.Arrays.copyOfR\u2026this, fromIndex, toIndex)");
        return copyOfRange;
    }
    
    @SinceKotlin(version = "1.3")
    @PublishedApi
    @JvmName(name = "copyOfRange")
    @NotNull
    public static final boolean[] copyOfRange(@NotNull final boolean[] $receiver, final int fromIndex, final int toIndex) {
        Intrinsics.checkParameterIsNotNull($receiver, "receiver$0");
        ArraysKt__ArraysJVMKt.copyOfRangeToIndexCheck(toIndex, $receiver.length);
        final boolean[] copyOfRange = Arrays.copyOfRange($receiver, fromIndex, toIndex);
        Intrinsics.checkExpressionValueIsNotNull(copyOfRange, "java.util.Arrays.copyOfR\u2026this, fromIndex, toIndex)");
        return copyOfRange;
    }
    
    @SinceKotlin(version = "1.3")
    @PublishedApi
    @JvmName(name = "copyOfRange")
    @NotNull
    public static final char[] copyOfRange(@NotNull final char[] $receiver, final int fromIndex, final int toIndex) {
        Intrinsics.checkParameterIsNotNull($receiver, "receiver$0");
        ArraysKt__ArraysJVMKt.copyOfRangeToIndexCheck(toIndex, $receiver.length);
        final char[] copyOfRange = Arrays.copyOfRange($receiver, fromIndex, toIndex);
        Intrinsics.checkExpressionValueIsNotNull(copyOfRange, "java.util.Arrays.copyOfR\u2026this, fromIndex, toIndex)");
        return copyOfRange;
    }
    
    public static final <T> void fill(@NotNull final T[] $receiver, final T element, final int fromIndex, final int toIndex) {
        Intrinsics.checkParameterIsNotNull($receiver, "receiver$0");
        Arrays.fill($receiver, fromIndex, toIndex, element);
    }
    
    public static final void fill(@NotNull final byte[] $receiver, final byte element, final int fromIndex, final int toIndex) {
        Intrinsics.checkParameterIsNotNull($receiver, "receiver$0");
        Arrays.fill($receiver, fromIndex, toIndex, element);
    }
    
    public static final void fill(@NotNull final short[] $receiver, final short element, final int fromIndex, final int toIndex) {
        Intrinsics.checkParameterIsNotNull($receiver, "receiver$0");
        Arrays.fill($receiver, fromIndex, toIndex, element);
    }
    
    public static final void fill(@NotNull final int[] $receiver, final int element, final int fromIndex, final int toIndex) {
        Intrinsics.checkParameterIsNotNull($receiver, "receiver$0");
        Arrays.fill($receiver, fromIndex, toIndex, element);
    }
    
    public static final void fill(@NotNull final long[] $receiver, final long element, final int fromIndex, final int toIndex) {
        Intrinsics.checkParameterIsNotNull($receiver, "receiver$0");
        Arrays.fill($receiver, fromIndex, toIndex, element);
    }
    
    public static final void fill(@NotNull final float[] $receiver, final float element, final int fromIndex, final int toIndex) {
        Intrinsics.checkParameterIsNotNull($receiver, "receiver$0");
        Arrays.fill($receiver, fromIndex, toIndex, element);
    }
    
    public static final void fill(@NotNull final double[] $receiver, final double element, final int fromIndex, final int toIndex) {
        Intrinsics.checkParameterIsNotNull($receiver, "receiver$0");
        Arrays.fill($receiver, fromIndex, toIndex, element);
    }
    
    public static final void fill(@NotNull final boolean[] $receiver, final boolean element, final int fromIndex, final int toIndex) {
        Intrinsics.checkParameterIsNotNull($receiver, "receiver$0");
        Arrays.fill($receiver, fromIndex, toIndex, element);
    }
    
    public static final void fill(@NotNull final char[] $receiver, final char element, final int fromIndex, final int toIndex) {
        Intrinsics.checkParameterIsNotNull($receiver, "receiver$0");
        Arrays.fill($receiver, fromIndex, toIndex, element);
    }
    
    @NotNull
    public static final <T> T[] plus(@NotNull final T[] $receiver, final T element) {
        Intrinsics.checkParameterIsNotNull($receiver, "receiver$0");
        final int index = $receiver.length;
        final Object[] result = Arrays.copyOf($receiver, index + 1);
        result[index] = element;
        final Object[] value = result;
        Intrinsics.checkExpressionValueIsNotNull(value, "result");
        return (T[])value;
    }
    
    @NotNull
    public static final byte[] plus(@NotNull final byte[] $receiver, final byte element) {
        Intrinsics.checkParameterIsNotNull($receiver, "receiver$0");
        final int index = $receiver.length;
        final byte[] result = Arrays.copyOf($receiver, index + 1);
        result[index] = element;
        final byte[] value = result;
        Intrinsics.checkExpressionValueIsNotNull(value, "result");
        return value;
    }
    
    @NotNull
    public static final short[] plus(@NotNull final short[] $receiver, final short element) {
        Intrinsics.checkParameterIsNotNull($receiver, "receiver$0");
        final int index = $receiver.length;
        final short[] result = Arrays.copyOf($receiver, index + 1);
        result[index] = element;
        final short[] value = result;
        Intrinsics.checkExpressionValueIsNotNull(value, "result");
        return value;
    }
    
    @NotNull
    public static final int[] plus(@NotNull final int[] $receiver, final int element) {
        Intrinsics.checkParameterIsNotNull($receiver, "receiver$0");
        final int index = $receiver.length;
        final int[] result = Arrays.copyOf($receiver, index + 1);
        result[index] = element;
        final int[] value = result;
        Intrinsics.checkExpressionValueIsNotNull(value, "result");
        return value;
    }
    
    @NotNull
    public static final long[] plus(@NotNull final long[] $receiver, final long element) {
        Intrinsics.checkParameterIsNotNull($receiver, "receiver$0");
        final int index = $receiver.length;
        final long[] result = Arrays.copyOf($receiver, index + 1);
        result[index] = element;
        final long[] value = result;
        Intrinsics.checkExpressionValueIsNotNull(value, "result");
        return value;
    }
    
    @NotNull
    public static final float[] plus(@NotNull final float[] $receiver, final float element) {
        Intrinsics.checkParameterIsNotNull($receiver, "receiver$0");
        final int index = $receiver.length;
        final float[] result = Arrays.copyOf($receiver, index + 1);
        result[index] = element;
        final float[] value = result;
        Intrinsics.checkExpressionValueIsNotNull(value, "result");
        return value;
    }
    
    @NotNull
    public static final double[] plus(@NotNull final double[] $receiver, final double element) {
        Intrinsics.checkParameterIsNotNull($receiver, "receiver$0");
        final int index = $receiver.length;
        final double[] result = Arrays.copyOf($receiver, index + 1);
        result[index] = element;
        final double[] value = result;
        Intrinsics.checkExpressionValueIsNotNull(value, "result");
        return value;
    }
    
    @NotNull
    public static final boolean[] plus(@NotNull final boolean[] $receiver, final boolean element) {
        Intrinsics.checkParameterIsNotNull($receiver, "receiver$0");
        final int index = $receiver.length;
        final boolean[] result = Arrays.copyOf($receiver, index + 1);
        result[index] = element;
        final boolean[] value = result;
        Intrinsics.checkExpressionValueIsNotNull(value, "result");
        return value;
    }
    
    @NotNull
    public static final char[] plus(@NotNull final char[] $receiver, final char element) {
        Intrinsics.checkParameterIsNotNull($receiver, "receiver$0");
        final int index = $receiver.length;
        final char[] result = Arrays.copyOf($receiver, index + 1);
        result[index] = element;
        final char[] value = result;
        Intrinsics.checkExpressionValueIsNotNull(value, "result");
        return value;
    }
    
    @NotNull
    public static final <T> T[] plus(@NotNull final T[] $receiver, @NotNull final Collection<? extends T> elements) {
        Intrinsics.checkParameterIsNotNull($receiver, "receiver$0");
        Intrinsics.checkParameterIsNotNull(elements, "elements");
        int index = $receiver.length;
        final Object[] result = Arrays.copyOf($receiver, index + elements.size());
        for (final Object element : elements) {
            result[index++] = element;
        }
        final Object[] value = result;
        Intrinsics.checkExpressionValueIsNotNull(value, "result");
        return (T[])value;
    }
    
    @NotNull
    public static final byte[] plus(@NotNull final byte[] $receiver, @NotNull final Collection<Byte> elements) {
        Intrinsics.checkParameterIsNotNull($receiver, "receiver$0");
        Intrinsics.checkParameterIsNotNull(elements, "elements");
        int index = $receiver.length;
        final byte[] result = Arrays.copyOf($receiver, index + elements.size());
        final Iterator<Byte> iterator = elements.iterator();
        while (iterator.hasNext()) {
            final byte element = iterator.next().byteValue();
            result[index++] = element;
        }
        final byte[] value = result;
        Intrinsics.checkExpressionValueIsNotNull(value, "result");
        return value;
    }
    
    @NotNull
    public static final short[] plus(@NotNull final short[] $receiver, @NotNull final Collection<Short> elements) {
        Intrinsics.checkParameterIsNotNull($receiver, "receiver$0");
        Intrinsics.checkParameterIsNotNull(elements, "elements");
        int index = $receiver.length;
        final short[] result = Arrays.copyOf($receiver, index + elements.size());
        final Iterator<Short> iterator = elements.iterator();
        while (iterator.hasNext()) {
            final short element = iterator.next().shortValue();
            result[index++] = element;
        }
        final short[] value = result;
        Intrinsics.checkExpressionValueIsNotNull(value, "result");
        return value;
    }
    
    @NotNull
    public static final int[] plus(@NotNull final int[] $receiver, @NotNull final Collection<Integer> elements) {
        Intrinsics.checkParameterIsNotNull($receiver, "receiver$0");
        Intrinsics.checkParameterIsNotNull(elements, "elements");
        int index = $receiver.length;
        final int[] result = Arrays.copyOf($receiver, index + elements.size());
        final Iterator<Integer> iterator = elements.iterator();
        while (iterator.hasNext()) {
            final int element = iterator.next().intValue();
            result[index++] = element;
        }
        final int[] value = result;
        Intrinsics.checkExpressionValueIsNotNull(value, "result");
        return value;
    }
    
    @NotNull
    public static final long[] plus(@NotNull final long[] $receiver, @NotNull final Collection<Long> elements) {
        Intrinsics.checkParameterIsNotNull($receiver, "receiver$0");
        Intrinsics.checkParameterIsNotNull(elements, "elements");
        int index = $receiver.length;
        final long[] result = Arrays.copyOf($receiver, index + elements.size());
        final Iterator<Long> iterator = elements.iterator();
        while (iterator.hasNext()) {
            final long element = iterator.next().longValue();
            result[index++] = element;
        }
        final long[] value = result;
        Intrinsics.checkExpressionValueIsNotNull(value, "result");
        return value;
    }
    
    @NotNull
    public static final float[] plus(@NotNull final float[] $receiver, @NotNull final Collection<Float> elements) {
        Intrinsics.checkParameterIsNotNull($receiver, "receiver$0");
        Intrinsics.checkParameterIsNotNull(elements, "elements");
        int index = $receiver.length;
        final float[] result = Arrays.copyOf($receiver, index + elements.size());
        final Iterator<Float> iterator = elements.iterator();
        while (iterator.hasNext()) {
            final float element = iterator.next().floatValue();
            result[index++] = element;
        }
        final float[] value = result;
        Intrinsics.checkExpressionValueIsNotNull(value, "result");
        return value;
    }
    
    @NotNull
    public static final double[] plus(@NotNull final double[] $receiver, @NotNull final Collection<Double> elements) {
        Intrinsics.checkParameterIsNotNull($receiver, "receiver$0");
        Intrinsics.checkParameterIsNotNull(elements, "elements");
        int index = $receiver.length;
        final double[] result = Arrays.copyOf($receiver, index + elements.size());
        final Iterator<Double> iterator = elements.iterator();
        while (iterator.hasNext()) {
            final double element = iterator.next().doubleValue();
            result[index++] = element;
        }
        final double[] value = result;
        Intrinsics.checkExpressionValueIsNotNull(value, "result");
        return value;
    }
    
    @NotNull
    public static final boolean[] plus(@NotNull final boolean[] $receiver, @NotNull final Collection<Boolean> elements) {
        Intrinsics.checkParameterIsNotNull($receiver, "receiver$0");
        Intrinsics.checkParameterIsNotNull(elements, "elements");
        int index = $receiver.length;
        final boolean[] result = Arrays.copyOf($receiver, index + elements.size());
        for (final boolean element : elements) {
            result[index++] = element;
        }
        final boolean[] value = result;
        Intrinsics.checkExpressionValueIsNotNull(value, "result");
        return value;
    }
    
    @NotNull
    public static final char[] plus(@NotNull final char[] $receiver, @NotNull final Collection<Character> elements) {
        Intrinsics.checkParameterIsNotNull($receiver, "receiver$0");
        Intrinsics.checkParameterIsNotNull(elements, "elements");
        int index = $receiver.length;
        final char[] result = Arrays.copyOf($receiver, index + elements.size());
        for (final char element : elements) {
            result[index++] = element;
        }
        final char[] value = result;
        Intrinsics.checkExpressionValueIsNotNull(value, "result");
        return value;
    }
    
    @NotNull
    public static final <T> T[] plus(@NotNull final T[] $receiver, @NotNull final T[] elements) {
        Intrinsics.checkParameterIsNotNull($receiver, "receiver$0");
        Intrinsics.checkParameterIsNotNull(elements, "elements");
        final int thisSize = $receiver.length;
        final int arraySize = elements.length;
        final Object[] result = Arrays.copyOf($receiver, thisSize + arraySize);
        System.arraycopy(elements, 0, result, thisSize, arraySize);
        final Object[] value = result;
        Intrinsics.checkExpressionValueIsNotNull(value, "result");
        return (T[])value;
    }
    
    @NotNull
    public static final byte[] plus(@NotNull final byte[] $receiver, @NotNull final byte[] elements) {
        Intrinsics.checkParameterIsNotNull($receiver, "receiver$0");
        Intrinsics.checkParameterIsNotNull(elements, "elements");
        final int thisSize = $receiver.length;
        final int arraySize = elements.length;
        final byte[] result = Arrays.copyOf($receiver, thisSize + arraySize);
        System.arraycopy(elements, 0, result, thisSize, arraySize);
        final byte[] value = result;
        Intrinsics.checkExpressionValueIsNotNull(value, "result");
        return value;
    }
    
    @NotNull
    public static final short[] plus(@NotNull final short[] $receiver, @NotNull final short[] elements) {
        Intrinsics.checkParameterIsNotNull($receiver, "receiver$0");
        Intrinsics.checkParameterIsNotNull(elements, "elements");
        final int thisSize = $receiver.length;
        final int arraySize = elements.length;
        final short[] result = Arrays.copyOf($receiver, thisSize + arraySize);
        System.arraycopy(elements, 0, result, thisSize, arraySize);
        final short[] value = result;
        Intrinsics.checkExpressionValueIsNotNull(value, "result");
        return value;
    }
    
    @NotNull
    public static final int[] plus(@NotNull final int[] $receiver, @NotNull final int[] elements) {
        Intrinsics.checkParameterIsNotNull($receiver, "receiver$0");
        Intrinsics.checkParameterIsNotNull(elements, "elements");
        final int thisSize = $receiver.length;
        final int arraySize = elements.length;
        final int[] result = Arrays.copyOf($receiver, thisSize + arraySize);
        System.arraycopy(elements, 0, result, thisSize, arraySize);
        final int[] value = result;
        Intrinsics.checkExpressionValueIsNotNull(value, "result");
        return value;
    }
    
    @NotNull
    public static final long[] plus(@NotNull final long[] $receiver, @NotNull final long[] elements) {
        Intrinsics.checkParameterIsNotNull($receiver, "receiver$0");
        Intrinsics.checkParameterIsNotNull(elements, "elements");
        final int thisSize = $receiver.length;
        final int arraySize = elements.length;
        final long[] result = Arrays.copyOf($receiver, thisSize + arraySize);
        System.arraycopy(elements, 0, result, thisSize, arraySize);
        final long[] value = result;
        Intrinsics.checkExpressionValueIsNotNull(value, "result");
        return value;
    }
    
    @NotNull
    public static final float[] plus(@NotNull final float[] $receiver, @NotNull final float[] elements) {
        Intrinsics.checkParameterIsNotNull($receiver, "receiver$0");
        Intrinsics.checkParameterIsNotNull(elements, "elements");
        final int thisSize = $receiver.length;
        final int arraySize = elements.length;
        final float[] result = Arrays.copyOf($receiver, thisSize + arraySize);
        System.arraycopy(elements, 0, result, thisSize, arraySize);
        final float[] value = result;
        Intrinsics.checkExpressionValueIsNotNull(value, "result");
        return value;
    }
    
    @NotNull
    public static final double[] plus(@NotNull final double[] $receiver, @NotNull final double[] elements) {
        Intrinsics.checkParameterIsNotNull($receiver, "receiver$0");
        Intrinsics.checkParameterIsNotNull(elements, "elements");
        final int thisSize = $receiver.length;
        final int arraySize = elements.length;
        final double[] result = Arrays.copyOf($receiver, thisSize + arraySize);
        System.arraycopy(elements, 0, result, thisSize, arraySize);
        final double[] value = result;
        Intrinsics.checkExpressionValueIsNotNull(value, "result");
        return value;
    }
    
    @NotNull
    public static final boolean[] plus(@NotNull final boolean[] $receiver, @NotNull final boolean[] elements) {
        Intrinsics.checkParameterIsNotNull($receiver, "receiver$0");
        Intrinsics.checkParameterIsNotNull(elements, "elements");
        final int thisSize = $receiver.length;
        final int arraySize = elements.length;
        final boolean[] result = Arrays.copyOf($receiver, thisSize + arraySize);
        System.arraycopy(elements, 0, result, thisSize, arraySize);
        final boolean[] value = result;
        Intrinsics.checkExpressionValueIsNotNull(value, "result");
        return value;
    }
    
    @NotNull
    public static final char[] plus(@NotNull final char[] $receiver, @NotNull final char[] elements) {
        Intrinsics.checkParameterIsNotNull($receiver, "receiver$0");
        Intrinsics.checkParameterIsNotNull(elements, "elements");
        final int thisSize = $receiver.length;
        final int arraySize = elements.length;
        final char[] result = Arrays.copyOf($receiver, thisSize + arraySize);
        System.arraycopy(elements, 0, result, thisSize, arraySize);
        final char[] value = result;
        Intrinsics.checkExpressionValueIsNotNull(value, "result");
        return value;
    }
    
    @InlineOnly
    private static final <T> T[] plusElement(@NotNull final T[] $receiver, final T element) {
        return (T[])plus($receiver, (Object)element);
    }
    
    public static final void sort(@NotNull final int[] $receiver) {
        Intrinsics.checkParameterIsNotNull($receiver, "receiver$0");
        if ($receiver.length > 1) {
            Arrays.sort($receiver);
        }
    }
    
    public static final void sort(@NotNull final long[] $receiver) {
        Intrinsics.checkParameterIsNotNull($receiver, "receiver$0");
        if ($receiver.length > 1) {
            Arrays.sort($receiver);
        }
    }
    
    public static final void sort(@NotNull final byte[] $receiver) {
        Intrinsics.checkParameterIsNotNull($receiver, "receiver$0");
        if ($receiver.length > 1) {
            Arrays.sort($receiver);
        }
    }
    
    public static final void sort(@NotNull final short[] $receiver) {
        Intrinsics.checkParameterIsNotNull($receiver, "receiver$0");
        if ($receiver.length > 1) {
            Arrays.sort($receiver);
        }
    }
    
    public static final void sort(@NotNull final double[] $receiver) {
        Intrinsics.checkParameterIsNotNull($receiver, "receiver$0");
        if ($receiver.length > 1) {
            Arrays.sort($receiver);
        }
    }
    
    public static final void sort(@NotNull final float[] $receiver) {
        Intrinsics.checkParameterIsNotNull($receiver, "receiver$0");
        if ($receiver.length > 1) {
            Arrays.sort($receiver);
        }
    }
    
    public static final void sort(@NotNull final char[] $receiver) {
        Intrinsics.checkParameterIsNotNull($receiver, "receiver$0");
        if ($receiver.length > 1) {
            Arrays.sort($receiver);
        }
    }
    
    @InlineOnly
    private static final <T extends Comparable<? super T>> void sort(@NotNull final T[] $receiver) {
        if ($receiver == null) {
            throw new TypeCastException("null cannot be cast to non-null type kotlin.Array<kotlin.Any?>");
        }
        sort((T[])$receiver);
    }
    
    public static final <T> void sort(@NotNull final T[] $receiver) {
        Intrinsics.checkParameterIsNotNull($receiver, "receiver$0");
        if ($receiver.length > 1) {
            Arrays.sort($receiver);
        }
    }
    
    public static final <T> void sort(@NotNull final T[] $receiver, final int fromIndex, final int toIndex) {
        Intrinsics.checkParameterIsNotNull($receiver, "receiver$0");
        Arrays.sort($receiver, fromIndex, toIndex);
    }
    
    public static final void sort(@NotNull final byte[] $receiver, final int fromIndex, final int toIndex) {
        Intrinsics.checkParameterIsNotNull($receiver, "receiver$0");
        Arrays.sort($receiver, fromIndex, toIndex);
    }
    
    public static final void sort(@NotNull final short[] $receiver, final int fromIndex, final int toIndex) {
        Intrinsics.checkParameterIsNotNull($receiver, "receiver$0");
        Arrays.sort($receiver, fromIndex, toIndex);
    }
    
    public static final void sort(@NotNull final int[] $receiver, final int fromIndex, final int toIndex) {
        Intrinsics.checkParameterIsNotNull($receiver, "receiver$0");
        Arrays.sort($receiver, fromIndex, toIndex);
    }
    
    public static final void sort(@NotNull final long[] $receiver, final int fromIndex, final int toIndex) {
        Intrinsics.checkParameterIsNotNull($receiver, "receiver$0");
        Arrays.sort($receiver, fromIndex, toIndex);
    }
    
    public static final void sort(@NotNull final float[] $receiver, final int fromIndex, final int toIndex) {
        Intrinsics.checkParameterIsNotNull($receiver, "receiver$0");
        Arrays.sort($receiver, fromIndex, toIndex);
    }
    
    public static final void sort(@NotNull final double[] $receiver, final int fromIndex, final int toIndex) {
        Intrinsics.checkParameterIsNotNull($receiver, "receiver$0");
        Arrays.sort($receiver, fromIndex, toIndex);
    }
    
    public static final void sort(@NotNull final char[] $receiver, final int fromIndex, final int toIndex) {
        Intrinsics.checkParameterIsNotNull($receiver, "receiver$0");
        Arrays.sort($receiver, fromIndex, toIndex);
    }
    
    public static final <T> void sortWith(@NotNull final T[] $receiver, @NotNull final Comparator<? super T> comparator) {
        Intrinsics.checkParameterIsNotNull($receiver, "receiver$0");
        Intrinsics.checkParameterIsNotNull(comparator, "comparator");
        if ($receiver.length > 1) {
            Arrays.sort($receiver, comparator);
        }
    }
    
    public static final <T> void sortWith(@NotNull final T[] $receiver, @NotNull final Comparator<? super T> comparator, final int fromIndex, final int toIndex) {
        Intrinsics.checkParameterIsNotNull($receiver, "receiver$0");
        Intrinsics.checkParameterIsNotNull(comparator, "comparator");
        Arrays.sort($receiver, fromIndex, toIndex, comparator);
    }
    
    @NotNull
    public static final Byte[] toTypedArray(@NotNull final byte[] $receiver) {
        // 
        // This method could not be decompiled.
        // 
        // Original Bytecode:
        // 
        //     1: ldc             "receiver$0"
        //     3: invokestatic    kotlin/jvm/internal/Intrinsics.checkParameterIsNotNull:(Ljava/lang/Object;Ljava/lang/String;)V
        //     6: aload_0         /* $receiver */
        //     7: arraylength    
        //     8: anewarray       Ljava/lang/Byte;
        //    11: astore_1        /* result */
        //    12: iconst_0       
        //    13: istore_2       
        //    14: aload_0         /* $receiver */
        //    15: arraylength    
        //    16: istore_3       
        //    17: iload_2        
        //    18: iload_3        
        //    19: if_icmpge       37
        //    22: aload_1         /* result */
        //    23: iload_2         /* index */
        //    24: aload_0         /* $receiver */
        //    25: iload_2         /* index */
        //    26: baload         
        //    27: invokestatic    java/lang/Byte.valueOf:(B)Ljava/lang/Byte;
        //    30: aastore        
        //    31: iinc            index, 1
        //    34: goto            17
        //    37: aload_1         /* result */
        //    38: areturn        
        //    StackMapTable: 00 02 FE 00 11 07 03 04 01 01 13
        // 
        // The error that occurred was:
        // 
        // java.lang.NullPointerException
        // 
        throw new IllegalStateException("An error occurred while decompiling this method.");
    }
    
    @NotNull
    public static final Short[] toTypedArray(@NotNull final short[] $receiver) {
        // 
        // This method could not be decompiled.
        // 
        // Original Bytecode:
        // 
        //     1: ldc             "receiver$0"
        //     3: invokestatic    kotlin/jvm/internal/Intrinsics.checkParameterIsNotNull:(Ljava/lang/Object;Ljava/lang/String;)V
        //     6: aload_0         /* $receiver */
        //     7: arraylength    
        //     8: anewarray       Ljava/lang/Short;
        //    11: astore_1        /* result */
        //    12: iconst_0       
        //    13: istore_2       
        //    14: aload_0         /* $receiver */
        //    15: arraylength    
        //    16: istore_3       
        //    17: iload_2        
        //    18: iload_3        
        //    19: if_icmpge       37
        //    22: aload_1         /* result */
        //    23: iload_2         /* index */
        //    24: aload_0         /* $receiver */
        //    25: iload_2         /* index */
        //    26: saload         
        //    27: invokestatic    java/lang/Short.valueOf:(S)Ljava/lang/Short;
        //    30: aastore        
        //    31: iinc            index, 1
        //    34: goto            17
        //    37: aload_1         /* result */
        //    38: areturn        
        //    StackMapTable: 00 02 FE 00 11 07 03 0C 01 01 13
        // 
        // The error that occurred was:
        // 
        // java.lang.NullPointerException
        // 
        throw new IllegalStateException("An error occurred while decompiling this method.");
    }
    
    @NotNull
    public static final Integer[] toTypedArray(@NotNull final int[] $receiver) {
        // 
        // This method could not be decompiled.
        // 
        // Original Bytecode:
        // 
        //     1: ldc             "receiver$0"
        //     3: invokestatic    kotlin/jvm/internal/Intrinsics.checkParameterIsNotNull:(Ljava/lang/Object;Ljava/lang/String;)V
        //     6: aload_0         /* $receiver */
        //     7: arraylength    
        //     8: anewarray       Ljava/lang/Integer;
        //    11: astore_1        /* result */
        //    12: iconst_0       
        //    13: istore_2       
        //    14: aload_0         /* $receiver */
        //    15: arraylength    
        //    16: istore_3       
        //    17: iload_2        
        //    18: iload_3        
        //    19: if_icmpge       37
        //    22: aload_1         /* result */
        //    23: iload_2         /* index */
        //    24: aload_0         /* $receiver */
        //    25: iload_2         /* index */
        //    26: iaload         
        //    27: invokestatic    java/lang/Integer.valueOf:(I)Ljava/lang/Integer;
        //    30: aastore        
        //    31: iinc            index, 1
        //    34: goto            17
        //    37: aload_1         /* result */
        //    38: areturn        
        //    StackMapTable: 00 02 FE 00 11 07 03 13 01 01 13
        // 
        // The error that occurred was:
        // 
        // java.lang.NullPointerException
        // 
        throw new IllegalStateException("An error occurred while decompiling this method.");
    }
    
    @NotNull
    public static final Long[] toTypedArray(@NotNull final long[] $receiver) {
        // 
        // This method could not be decompiled.
        // 
        // Original Bytecode:
        // 
        //     1: ldc             "receiver$0"
        //     3: invokestatic    kotlin/jvm/internal/Intrinsics.checkParameterIsNotNull:(Ljava/lang/Object;Ljava/lang/String;)V
        //     6: aload_0         /* $receiver */
        //     7: arraylength    
        //     8: anewarray       Ljava/lang/Long;
        //    11: astore_1        /* result */
        //    12: iconst_0       
        //    13: istore_2       
        //    14: aload_0         /* $receiver */
        //    15: arraylength    
        //    16: istore_3       
        //    17: iload_2        
        //    18: iload_3        
        //    19: if_icmpge       37
        //    22: aload_1         /* result */
        //    23: iload_2         /* index */
        //    24: aload_0         /* $receiver */
        //    25: iload_2         /* index */
        //    26: laload         
        //    27: invokestatic    java/lang/Long.valueOf:(J)Ljava/lang/Long;
        //    30: aastore        
        //    31: iinc            index, 1
        //    34: goto            17
        //    37: aload_1         /* result */
        //    38: areturn        
        //    StackMapTable: 00 02 FE 00 11 07 03 1A 01 01 13
        // 
        // The error that occurred was:
        // 
        // java.lang.NullPointerException
        // 
        throw new IllegalStateException("An error occurred while decompiling this method.");
    }
    
    @NotNull
    public static final Float[] toTypedArray(@NotNull final float[] $receiver) {
        // 
        // This method could not be decompiled.
        // 
        // Original Bytecode:
        // 
        //     1: ldc             "receiver$0"
        //     3: invokestatic    kotlin/jvm/internal/Intrinsics.checkParameterIsNotNull:(Ljava/lang/Object;Ljava/lang/String;)V
        //     6: aload_0         /* $receiver */
        //     7: arraylength    
        //     8: anewarray       Ljava/lang/Float;
        //    11: astore_1        /* result */
        //    12: iconst_0       
        //    13: istore_2       
        //    14: aload_0         /* $receiver */
        //    15: arraylength    
        //    16: istore_3       
        //    17: iload_2        
        //    18: iload_3        
        //    19: if_icmpge       37
        //    22: aload_1         /* result */
        //    23: iload_2         /* index */
        //    24: aload_0         /* $receiver */
        //    25: iload_2         /* index */
        //    26: faload         
        //    27: invokestatic    java/lang/Float.valueOf:(F)Ljava/lang/Float;
        //    30: aastore        
        //    31: iinc            index, 1
        //    34: goto            17
        //    37: aload_1         /* result */
        //    38: areturn        
        //    StackMapTable: 00 02 FE 00 11 07 03 21 01 01 13
        // 
        // The error that occurred was:
        // 
        // java.lang.NullPointerException
        // 
        throw new IllegalStateException("An error occurred while decompiling this method.");
    }
    
    @NotNull
    public static final Double[] toTypedArray(@NotNull final double[] $receiver) {
        // 
        // This method could not be decompiled.
        // 
        // Original Bytecode:
        // 
        //     1: ldc             "receiver$0"
        //     3: invokestatic    kotlin/jvm/internal/Intrinsics.checkParameterIsNotNull:(Ljava/lang/Object;Ljava/lang/String;)V
        //     6: aload_0         /* $receiver */
        //     7: arraylength    
        //     8: anewarray       Ljava/lang/Double;
        //    11: astore_1        /* result */
        //    12: iconst_0       
        //    13: istore_2       
        //    14: aload_0         /* $receiver */
        //    15: arraylength    
        //    16: istore_3       
        //    17: iload_2        
        //    18: iload_3        
        //    19: if_icmpge       37
        //    22: aload_1         /* result */
        //    23: iload_2         /* index */
        //    24: aload_0         /* $receiver */
        //    25: iload_2         /* index */
        //    26: daload         
        //    27: invokestatic    java/lang/Double.valueOf:(D)Ljava/lang/Double;
        //    30: aastore        
        //    31: iinc            index, 1
        //    34: goto            17
        //    37: aload_1         /* result */
        //    38: areturn        
        //    StackMapTable: 00 02 FE 00 11 07 03 28 01 01 13
        // 
        // The error that occurred was:
        // 
        // java.lang.NullPointerException
        // 
        throw new IllegalStateException("An error occurred while decompiling this method.");
    }
    
    @NotNull
    public static final Boolean[] toTypedArray(@NotNull final boolean[] $receiver) {
        // 
        // This method could not be decompiled.
        // 
        // Original Bytecode:
        // 
        //     1: ldc             "receiver$0"
        //     3: invokestatic    kotlin/jvm/internal/Intrinsics.checkParameterIsNotNull:(Ljava/lang/Object;Ljava/lang/String;)V
        //     6: aload_0         /* $receiver */
        //     7: arraylength    
        //     8: anewarray       Ljava/lang/Boolean;
        //    11: astore_1        /* result */
        //    12: iconst_0       
        //    13: istore_2       
        //    14: aload_0         /* $receiver */
        //    15: arraylength    
        //    16: istore_3       
        //    17: iload_2        
        //    18: iload_3        
        //    19: if_icmpge       37
        //    22: aload_1         /* result */
        //    23: iload_2         /* index */
        //    24: aload_0         /* $receiver */
        //    25: iload_2         /* index */
        //    26: baload         
        //    27: invokestatic    java/lang/Boolean.valueOf:(Z)Ljava/lang/Boolean;
        //    30: aastore        
        //    31: iinc            index, 1
        //    34: goto            17
        //    37: aload_1         /* result */
        //    38: areturn        
        //    StackMapTable: 00 02 FE 00 11 07 03 2D 01 01 13
        // 
        // The error that occurred was:
        // 
        // java.lang.NullPointerException
        // 
        throw new IllegalStateException("An error occurred while decompiling this method.");
    }
    
    @NotNull
    public static final Character[] toTypedArray(@NotNull final char[] $receiver) {
        // 
        // This method could not be decompiled.
        // 
        // Original Bytecode:
        // 
        //     1: ldc             "receiver$0"
        //     3: invokestatic    kotlin/jvm/internal/Intrinsics.checkParameterIsNotNull:(Ljava/lang/Object;Ljava/lang/String;)V
        //     6: aload_0         /* $receiver */
        //     7: arraylength    
        //     8: anewarray       Ljava/lang/Character;
        //    11: astore_1        /* result */
        //    12: iconst_0       
        //    13: istore_2       
        //    14: aload_0         /* $receiver */
        //    15: arraylength    
        //    16: istore_3       
        //    17: iload_2        
        //    18: iload_3        
        //    19: if_icmpge       37
        //    22: aload_1         /* result */
        //    23: iload_2         /* index */
        //    24: aload_0         /* $receiver */
        //    25: iload_2         /* index */
        //    26: caload         
        //    27: invokestatic    java/lang/Character.valueOf:(C)Ljava/lang/Character;
        //    30: aastore        
        //    31: iinc            index, 1
        //    34: goto            17
        //    37: aload_1         /* result */
        //    38: areturn        
        //    StackMapTable: 00 02 FE 00 11 07 03 32 01 01 13
        // 
        // The error that occurred was:
        // 
        // java.lang.NullPointerException
        // 
        throw new IllegalStateException("An error occurred while decompiling this method.");
    }
    
    @NotNull
    public static final <T extends Comparable<? super T>> SortedSet<T> toSortedSet(@NotNull final T[] $receiver) {
        Intrinsics.checkParameterIsNotNull($receiver, "receiver$0");
        return ArraysKt___ArraysKt.toCollection($receiver, new TreeSet<T>());
    }
    
    @NotNull
    public static final SortedSet<Byte> toSortedSet(@NotNull final byte[] $receiver) {
        Intrinsics.checkParameterIsNotNull($receiver, "receiver$0");
        return ArraysKt___ArraysKt.toCollection($receiver, new TreeSet<Byte>());
    }
    
    @NotNull
    public static final SortedSet<Short> toSortedSet(@NotNull final short[] $receiver) {
        Intrinsics.checkParameterIsNotNull($receiver, "receiver$0");
        return ArraysKt___ArraysKt.toCollection($receiver, new TreeSet<Short>());
    }
    
    @NotNull
    public static final SortedSet<Integer> toSortedSet(@NotNull final int[] $receiver) {
        Intrinsics.checkParameterIsNotNull($receiver, "receiver$0");
        return ArraysKt___ArraysKt.toCollection($receiver, new TreeSet<Integer>());
    }
    
    @NotNull
    public static final SortedSet<Long> toSortedSet(@NotNull final long[] $receiver) {
        Intrinsics.checkParameterIsNotNull($receiver, "receiver$0");
        return ArraysKt___ArraysKt.toCollection($receiver, new TreeSet<Long>());
    }
    
    @NotNull
    public static final SortedSet<Float> toSortedSet(@NotNull final float[] $receiver) {
        Intrinsics.checkParameterIsNotNull($receiver, "receiver$0");
        return ArraysKt___ArraysKt.toCollection($receiver, new TreeSet<Float>());
    }
    
    @NotNull
    public static final SortedSet<Double> toSortedSet(@NotNull final double[] $receiver) {
        Intrinsics.checkParameterIsNotNull($receiver, "receiver$0");
        return ArraysKt___ArraysKt.toCollection($receiver, new TreeSet<Double>());
    }
    
    @NotNull
    public static final SortedSet<Boolean> toSortedSet(@NotNull final boolean[] $receiver) {
        Intrinsics.checkParameterIsNotNull($receiver, "receiver$0");
        return ArraysKt___ArraysKt.toCollection($receiver, new TreeSet<Boolean>());
    }
    
    @NotNull
    public static final SortedSet<Character> toSortedSet(@NotNull final char[] $receiver) {
        Intrinsics.checkParameterIsNotNull($receiver, "receiver$0");
        return ArraysKt___ArraysKt.toCollection($receiver, new TreeSet<Character>());
    }
    
    @NotNull
    public static final <T> SortedSet<T> toSortedSet(@NotNull final T[] $receiver, @NotNull final Comparator<? super T> comparator) {
        Intrinsics.checkParameterIsNotNull($receiver, "receiver$0");
        Intrinsics.checkParameterIsNotNull(comparator, "comparator");
        return ArraysKt___ArraysKt.toCollection($receiver, new TreeSet<T>(comparator));
    }
    
    public ArraysKt___ArraysJvmKt() {
    }
}
